Workbook

Sheet Start Here
A1: WELCOME — YOUR RENTAL PROPERTY SPREADSHEET
A2: One organized system for 1–10 rental properties: rent due vs. paid (with real partial-payment and carried-balance tracking), income & expenses, maintenance, deposits, capital improvements, a portfolio dashboard, and a year-end summary. Pre-loaded with realistic sample data so you can see it working before you enter your own numbers.
A4: Step 0 — Go to File > Make a Copy to save this to your own Google Drive. Always work from your own copy, never the original.
A6: QUICK NAVIGATION — click a tab name to jump there
A7: → Properties & Units
A8: → Tenants & Leases
A9: → Rent Tracker
A10: → Income & Expenses
A11: → Maintenance & Repairs
A12: → Deposits & Capital Improvements
A13: → Dashboard
A14: → Year-End Summary
... A24: WHAT THE COLORS MEAN
A25: YELLOW | B25: YOU TYPE HERE.
A26: WHITE | B26: AUTOMATIC — calculated for you. Don't type over these.
A28: Google Sheets & Excel compatible — both included. Works on any computer, no software to install for the Google Sheets version.
A30: DISCLAIMER: This is an organizational and bookkeeping template only. It is not legal, tax, or accounting advice, and does not guarantee compliance with any landlord-tenant law. Always consult a qualified professional for legal or tax questions.

Sheet Properties & Units
A1: PROPERTIES & UNITS
A3: Property ID | B3: Property Name | C3: Address | D3: Unit ID | E3: Unit Name/Number | F3: Property Type | G3: Ownership % | H3: Purchase Date | I3: Purchase Price | J3: Current Status | K3: Notes
A4: P1 | B4: Maple Ave Duplex | C4: 123 Maple Ave, Springfield | D4: P1-U1 | E4: Unit 1 | F4: Duplex | G4: 1 | H4: 44621 | I4: 285000 | J4: Occupied
A5: P1 | B5: Maple Ave Duplex | C5: 123 Maple Ave, Springfield | D5: P1-U2 | E5: Unit 2 | F5: Duplex | G5: 1 | H5: 44621 | I5: 285000 | J5: Occupied
A6: P2 | B6: Oak Street Fourplex | C6: 456 Oak St, Springfield | D6: P2-U1 | E6: Unit A | F6: Fourplex | G6: 1 | H6: 44392 | I6: 410000 | J6: Occupied
A7: P2 | B7: Oak Street Fourplex | C7: 456 Oak St, Springfield | D7: P2-U2 | E7: Unit B | F7: Fourplex | G7: 1 | H7: 44392 | I7: 410000 | J7: Vacant
A8: P3 | B8: Elm Court House | C8: 789 Elm Ct, Springfield | D8: P3-U1 | E8: Main House | F8: Single-Family | G8: 1 | H8: 44936 | I8: 325000 | J8: Occupied

Sheet Tenants & Leases
A1: TENANTS & LEASES
A3: Tenant ID | B3: Property ID | C3: Unit ID | D3: Tenant Name | E3: Lease Start | F3: Lease End | G3: Monthly Rent | H3: Security Deposit | I3: Deposit Received Date | J3: Deposit Returned Date | K3: Deposit Returned Amount | L3: Lease Status | M3: Contact/Notes
A4: T1 | B4: P1 | C4: P1-U1 | D4: John Smith | E4: 45658 | F4: 46387 | G4: 1500 | H4: 1500 | I4: 45658 | L4: Active | M4: =IF(AND($F4<>"",$F4<TODAY(),$L4="Active"),"⚠ lease end date passed but still marked Active",IF(AND($F4<>"",$F4>=TODAY(),$F4-TODAY()<=60,$L4="Active"),"⚠ lease expiring within 60 days",""))
A5: T2 | B5: P1 | C5: P1-U2 | D5: Maria Lopez | E5: 45689 | F5: 46053 | G5: 1200 | H5: 1200 | I5: 45689 | J5: 46208 | K5: 1100 | L5: Vacated | M5: =IF(AND($F5<>"",$F5<TODAY(),$L5="Active"),"⚠ lease end date passed but still marked Active",IF(AND($F5<>"",$F5>=TODAY(),$F5-TODAY()<=60,$L5="Active"),"⚠ lease expiring within 60 days",""))
A6: T2B | B6: P1 | C6: P1-U2 | D6: Aisha Bello | E6: 46204 | F6: 46568 | G6: 1250 | H6: 1250 | I6: 46204 | L6: Active | M6: =IF(AND($F6<>"",$F6<TODAY(),$L6="Active"),"⚠ lease end date passed but still marked Active",IF(AND($F6<>"",$F6>=TODAY(),$F6-TODAY()<=60,$L6="Active"),"⚠ lease expiring within 60 days",""))
A7: T3 | B7: P2 | C7: P2-U1 | D7: David Chen | E7: 45383 | F7: 46326 | G7: 1200 | H7: 1200 | I7: 45383 | L7: Active | M7: =IF(AND($F7<>"",$F7<TODAY(),$L7="Active"),"⚠ lease end date passed but still marked Active",IF(AND($F7<>"",$F7>=TODAY(),$F7-TODAY()<=60,$L7="Active"),"⚠ lease expiring within 60 days",""))
A8: T4 | B8: P2 | C8: P2-U2 | G8: 0 | H8: 0 | L8: Vacant | M8: =IF(AND($F8<>"",$F8<TODAY(),$L8="Active"),"⚠ lease end date passed but still marked Active",IF(AND($F8<>"",$F8>=TODAY(),$F8-TODAY()<=60,$L8="Active"),"⚠ lease expiring within 60 days",""))
A9: T5 | B9: P3 | C9: P3-U1 | D9: Priya Patel | E9: 45901 | F9: 46310 | G9: 1900 | H9: 1900 | I9: 45901 | L9: Active | M9: =IF(AND($F9<>"",$F9<TODAY(),$L9="Active"),"⚠ lease end date passed but still marked Active",IF(AND($F9<>"",$F9>=TODAY(),$F9-TODAY()<=60,$L9="Active"),"⚠ lease expiring within 60 days",""))
A10: T4B | B10: P2 | C10: P2-U2 | D10: Marcus Webb | E10: 46204 | F10: 46568 | G10: 1100 | H10: 1100 | I10: 46204 | L10: Active | M10: =IF(AND($F10<>"",$F10<TODAY(),$L10="Active"),"⚠ lease end date passed but still marked Active",IF(AND($F10<>"",$F10>=TODAY(),$F10-TODAY()<=60,$L10="Active"),"⚠ lease expiring within 60 days",""))
M11: =IF(AND($F11<>"",$F11<TODAY(),$L11="Active"),"⚠ lease end date passed but still marked Active",IF(AND($F11<>"",$F11>=TODAY(),$F11-TODAY()<=60,$L11="Active"),"⚠ lease expiring within 60 days",""))
M12: =IF(AND($F12<>"",$F12<TODAY(),$L12="Active"),"⚠ lease end date passed but still marked Active",IF(AND($F12<>"",$F12>=TODAY(),$F12-TODAY()<=60,$L12="Active"),"⚠ lease expiring within 60 days",""))
M13: =IF(AND($F13<>"",$F13<TODAY(),$L13="Active"),"⚠ lease end date passed but still marked Active",IF(AND($F13<>"",$F13>=TODAY(),$F13-TODAY()<=60,$L13="Active"),"⚠ lease expiring within 60 days",""))
M14: =IF(AND($F14<>"",$F14<TODAY(),$L14="Active"),"⚠ lease end date passed but still marked Active",IF(AND($F14<>"",$F14>=TODAY(),$F14-TODAY()<=60,$L14="Active"),"⚠ lease expiring within 60 days",""))
M15: =IF(AND($F15<>"",$F15<TODAY(),$L15="Active"),"⚠ lease end date passed but still marked Active",IF(AND($F15<>"",$F15>=TODAY(),$F15-TODAY()<=60,$L15="Active"),"⚠ lease expiring within 60 days",""))
M16: =IF(AND($F16<>"",$F16<TODAY(),$L16="Active"),"⚠ lease end date passed but still marked Active",IF(AND($F16<>"",$F16>=TODAY(),$F16-TODAY()<=60,$L16="Active"),"⚠ lease expiring within 60 days",""))
M17: =IF(AND($F17<>"",$F17<TODAY(),$L17="Active"),"⚠ lease end date passed but still marked Active",IF(AND($F17<>"",$F17>=TODAY(),$F17-TODAY()<=60,$L17="Active"),"⚠ lease expiring within 60 days",""))
M18: =IF(AND($F18<>"",$F18<TODAY(),$L18="Active"),"⚠ lease end date passed but still marked Active",IF(AND($F18<>"",$F18>=TODAY(),$F18-TODAY()<=60,$L18="Active"),"⚠ lease expiring within 60 days",""))
M19: =IF(AND($F19<>"",$F19<TODAY(),$L19="Active"),"⚠ lease end date passed but still marked Active",IF(AND($F19<>"",$F19>=TODAY(),$F19-TODAY()<=60,$L19="Active"),"⚠ lease expiring within 60 days",""))
M20: =IF(AND($F20<>"",$F20<TODAY(),$L20="Active"),"⚠ lease end date passed but still marked Active",IF(AND($F20<>"",$F20>=TODAY(),$F20-TODAY()<=60,$L20="Active"),"⚠ lease expiring within 60 days",""))
M21: =IF(AND($F21<>"",$F21<TODAY(),$L21="Active"),"⚠ lease end date passed but still marked Active",IF(AND($F21<>"",$F21>=TODAY(),$F21-TODAY()<=60,$L21="Active"),"⚠ lease expiring within 60 days",""))
M22: =IF(AND($F22<>"",$F22<TODAY(),$L22="Active"),"⚠ lease end date passed but still marked Active",IF(AND($F22<>"",$F22>=TODAY(),$F22-TODAY()<=60,$L22="Active"),"⚠ lease expiring within 60 days",""))
... M38: =IF(AND($F38<>"",$F38<TODAY(),$L38="Active"),"⚠ lease end date passed but still marked Active",IF(AND($F38<>"",$F38>=TODAY(),$F38-TODAY()<=60,$L38="Active"),"⚠ lease expiring within 60 days",""))
A40: Column M shows an automatic flag; column L (Lease Status) is entered by you.

Sheet Rent Tracker
A1: RENT TRACKER
A2: One row per unit per month, entered in date order. Prior Balance carries forward automatically from the row above for the same unit — partial payments, missed months, and overpayments (credits) are all tracked correctly. Add a new block of rows for each additional unit; keep each unit's rows together and in month order.
A3: Month | B3: Property | C3: Unit | D3: Tenant | E3: Base Rent Due | F3: Prior Balance | G3: Total Due | H3: Payment 1 | I3: Payment 1 Date | J3: Payment 2 | K3: Payment 2 Date | L3: Payment 3 | M3: Payment 3 Date | N3: Total Paid | O3: Remaining Balance | P3: Payment Status | Q3: Notes
A4: 46113 | B4: P1 | C4: P1-U1 | D4: T1 | E4: 1500 | F4: 0 | G4: =E4+F4 | H4: 1500 | I4: 46115 | N4: =SUM(IF(ISNUMBER(H4),H4,0),IF(ISNUMBER(J4),J4,0),IF(ISNUMBER(L4),L4,0)) | O4: =G4-N4 | P4: =IF(AND($D4="",E4=0,F4=0),"Vacant",IF(O4<-0.004,"Overpaid / Credit",IF(O4<=0.004,"Paid",IF(N4<=0.004,"Unpaid","Partial"))))
A5: 46143 | B5: P1 | C5: P1-U1 | D5: T1 | E5: 1500 | F5: =O4 | G5: =E5+F5 | H5: 1000 | I5: 46146 | N5: =SUM(IF(ISNUMBER(H5),H5,0),IF(ISNUMBER(J5),J5,0),IF(ISNUMBER(L5),L5,0)) | O5: =G5-N5 | P5: =IF(AND($D5="",E5=0,F5=0),"Vacant",IF(O5<-0.004,"Overpaid / Credit",IF(O5<=0.004,"Paid",IF(N5<=0.004,"Unpaid","Partial"))))
A6: 46174 | B6: P1 | C6: P1-U1 | D6: T1 | E6: 1500 | F6: =O5 | G6: =E6+F6 | H6: 600 | I6: 46175 | J6: 400 | K6: 46193 | N6: =SUM(IF(ISNUMBER(H6),H6,0),IF(ISNUMBER(J6),J6,0),IF(ISNUMBER(L6),L6,0)) | O6: =G6-N6 | P6: =IF(AND($D6="",E6=0,F6=0),"Vacant",IF(O6<-0.004,"Overpaid / Credit",IF(O6<=0.004,"Paid",IF(N6<=0.004,"Unpaid","Partial"))))
A7: 46204 | B7: P1 | C7: P1-U1 | D7: T1 | E7: 1500 | F7: =O6 | G7: =E7+F7 | N7: =SUM(IF(ISNUMBER(H7),H7,0),IF(ISNUMBER(J7),J7,0),IF(ISNUMBER(L7),L7,0)) | O7: =G7-N7 | P7: =IF(AND($D7="",E7=0,F7=0),"Vacant",IF(O7<-0.004,"Overpaid / Credit",IF(O7<=0.004,"Paid",IF(N7<=0.004,"Unpaid","Partial"))))
A8: 46235 | B8: P1 | C8: P1-U1 | D8: T1 | E8: 1500 | F8: =O7 | G8: =E8+F8 | H8: 4900 | I8: 46239 | N8: =SUM(IF(ISNUMBER(H8),H8,0),IF(ISNUMBER(J8),J8,0),IF(ISNUMBER(L8),L8,0)) | O8: =G8-N8 | P8: =IF(AND($D8="",E8=0,F8=0),"Vacant",IF(O8<-0.004,"Overpaid / Credit",IF(O8<=0.004,"Paid",IF(N8<=0.004,"Unpaid","Partial"))))
A9: 46266 | B9: P1 | C9: P1-U1 | D9: T1 | E9: 1500 | F9: =O8 | G9: =E9+F9 | H9: 1000 | I9: 46268 | N9: =SUM(IF(ISNUMBER(H9),H9,0),IF(ISNUMBER(J9),J9,0),IF(ISNUMBER(L9),L9,0)) | O9: =G9-N9 | P9: =IF(AND($D9="",E9=0,F9=0),"Vacant",IF(O9<-0.004,"Overpaid / Credit",IF(O9<=0.004,"Paid",IF(N9<=0.004,"Unpaid","Partial"))))
A10: 46113 | B10: P1 | C10: P1-U2 | D10: T2 | E10: 1200 | F10: 0 | G10: =E10+F10 | H10: 1200 | I10: 46113 | N10: =SUM(IF(ISNUMBER(H10),H10,0),IF(ISNUMBER(J10),J10,0),IF(ISNUMBER(L10),L10,0)) | O10: =G10-N10 | P10: =IF(AND($D10="",E10=0,F10=0),"Vacant",IF(O10<-0.004,"Overpaid / Credit",IF(O10<=0.004,"Paid",IF(N10<=0.004,"Unpaid","Partial"))))
A11: 46143 | B11: P1 | C11: P1-U2 | D11: T2 | E11: 1200 | F11: =O10 | G11: =E11+F11 | H11: 1200 | I11: 46143 | N11: =SUM(IF(ISNUMBER(H11),H11,0),IF(ISNUMBER(J11),J11,0),IF(ISNUMBER(L11),L11,0)) | O11: =G11-N11 | P11: =IF(AND($D11="",E11=0,F11=0),"Vacant",IF(O11<-0.004,"Overpaid / Credit",IF(O11<=0.004,"Paid",IF(N11<=0.004,"Unpaid","Partial"))))
A12: 46174 | B12: P1 | C12: P1-U2 | E12: 0 | F12: =O11 | G12: =E12+F12 | N12: =SUM(IF(ISNUMBER(H12),H12,0),IF(ISNUMBER(J12),J12,0),IF(ISNUMBER(L12),L12,0)) | O12: =G12-N12 | P12: =IF(AND($D12="",E12=0,F12=0),"Vacant",IF(O12<-0.004,"Overpaid / Credit",IF(O12<=0.004,"Paid",IF(N12<=0.004,"Unpaid","Partial"))))
A13: 46204 | B13: P1 | C13: P1-U2 | D13: T2B | E13: 1250 | F13: =O12 | G13: =E13+F13 | H13: 1250 | I13: 46204 | N13: =SUM(IF(ISNUMBER(H13),H13,0),IF(ISNUMBER(J13),J13,0),IF(ISNUMBER(L13),L13,0)) | O13: =G13-N13 | P13: =IF(AND($D13="",E13=0,F13=0),"Vacant",IF(O13<-0.004,"Overpaid / Credit",IF(O13<=0.004,"Paid",IF(N13<=0.004,"Unpaid","Partial"))))
A14: 46235 | B14: P1 | C14: P1-U2 | D14: T2B | E14: 1250 | F14: =O13 | G14: =E14+F14 | H14: 1250 | I14: 46235 | N14: =SUM(IF(ISNUMBER(H14),H14,0),IF(ISNUMBER(J14),J14,0),IF(ISNUMBER(L14),L14,0)) | O14: =G14-N14 | P14: =IF(AND($D14="",E14=0,F14=0),"Vacant",IF(O14<-0.004,"Overpaid / Credit",IF(O14<=0.004,"Paid",IF(N14<=0.004,"Unpaid","Partial"))))
A15: 46266 | B15: P1 | C15: P1-U2 | D15: T2B | E15: 1250 | F15: =O14 | G15: =E15+F15 | H15: 1250 | I15: 46266 | N15: =SUM(IF(ISNUMBER(H15),H15,0),IF(ISNUMBER(J15),J15,0),IF(ISNUMBER(L15),L15,0)) | O15: =G15-N15 | P15: =IF(AND($D15="",E15=0,F15=0),"Vacant",IF(O15<-0.004,"Overpaid / Credit",IF(O15<=0.004,"Paid",IF(N15<=0.004,"Unpaid","Partial"))))
A16: 46113 | B16: P2 | C16: P2-U1 | D16: T3 | E16: 1200 | F16: 0 | G16: =E16+F16 | H16: 1200 | I16: 46117 | N16: =SUM(IF(ISNUMBER(H16),H16,0),IF(ISNUMBER(J16),J16,0),IF(ISNUMBER(L16),L16,0)) | O16: =G16-N16 | P16: =IF(AND($D16="",E16=0,F16=0),"Vacant",IF(O16<-0.004,"Overpaid / Credit",IF(O16<=0.004,"Paid",IF(N16<=0.004,"Unpaid","Partial"))))
A17: 46143 | B17: P2 | C17: P2-U1 | D17: T3 | E17: 1200 | F17: =O16 | G17: =E17+F17 | H17: 1200 | I17: 46147 | N17: =SUM(IF(ISNUMBER(H17),H17,0),IF(ISNUMBER(J17),J17,0),IF(ISNUMBER(L17),L17,0)) | O17: =G17-N17 | P17: =IF(AND($D17="",E17=0,F17=0),"Vacant",IF(O17<-0.004,"Overpaid / Credit",IF(O17<=0.004,"Paid",IF(N17<=0.004,"Unpaid","Partial"))))
A18: 46174 | B18: P2 | C18: P2-U1 | D18: T3 | E18: 1200 | F18: =O17 | G18: =E18+F18 | H18: 1200 | I18: 46178 | N18: =SUM(IF(ISNUMBER(H18),H18,0),IF(ISNUMBER(J18),J18,0),IF(ISNUMBER(L18),L18,0)) | O18: =G18-N18 | P18: =IF(AND($D18="",E18=0,F18=0),"Vacant",IF(O18<-0.004,"Overpaid / Credit",IF(O18<=0.004,"Paid",IF(N18<=0.004,"Unpaid","Partial"))))
A19: 46204 | B19: P2 | C19: P2-U1 | D19: T3 | E19: 1300 | F19: =O18 | G19: =E19+F19 | H19: 1300 | I19: 46208 | N19: =SUM(IF(ISNUMBER(H19),H19,0),IF(ISNUMBER(J19),J19,0),IF(ISNUMBER(L19),L19,0)) | O19: =G19-N19 | P19: =IF(AND($D19="",E19=0,F19=0),"Vacant",IF(O19<-0.004,"Overpaid / Credit",IF(O19<=0.004,"Paid",IF(N19<=0.004,"Unpaid","Partial"))))
A20: 46235 | B20: P2 | C20: P2-U1 | D20: T3 | E20: 1300 | F20: =O19 | G20: =E20+F20 | H20: 1300 | I20: 46239 | N20: =SUM(IF(ISNUMBER(H20),H20,0),IF(ISNUMBER(J20),J20,0),IF(ISNUMBER(L20),L20,0)) | O20: =G20-N20 | P20: =IF(AND($D20="",E20=0,F20=0),"Vacant",IF(O20<-0.004,"Overpaid / Credit",IF(O20<=0.004,"Paid",IF(N20<=0.004,"Unpaid","Partial"))))
A21: 46266 | B21: P2 | C21: P2-U1 | D21: T3 | E21: 1300 | F21: =O20 | G21: =E21+F21 | H21: 1300 | I21: 46270 | N21: =SUM(IF(ISNUMBER(H21),H21,0),IF(ISNUMBER(J21),J21,0),IF(ISNUMBER(L21),L21,0)) | O21: =G21-N21 | P21: =IF(AND($D21="",E21=0,F21=0),"Vacant",IF(O21<-0.004,"Overpaid / Credit",IF(O21<=0.004,"Paid",IF(N21<=0.004,"Unpaid","Partial"))))
A22: 46113 | B22: P2 | C22: P2-U2 | E22: 0 | F22: 0 | G22: =E22+F22 | N22: =SUM(IF(ISNUMBER(H22),H22,0),IF(ISNUMBER(J22),J22,0),IF(ISNUMBER(L22),L22,0)) | O22: =G22-N22 | P22: =IF(AND($D22="",E22=0,F22=0),"Vacant",IF(O22<-0.004,"Overpaid / Credit",IF(O22<=0.004,"Paid",IF(N22<=0.004,"Unpaid","Partial"))))
A23: 46143 | B23: P2 | C23: P2-U2 | E23: 0 | F23: =O22 | G23: =E23+F23 | N23: =SUM(IF(ISNUMBER(H23),H23,0),IF(ISNUMBER(J23),J23,0),IF(ISNUMBER(L23),L23,0)) | O23: =G23-N23 | P23: =IF(AND($D23="",E23=0,F23=0),"Vacant",IF(O23<-0.004,"Overpaid / Credit",IF(O23<=0.004,"Paid",IF(N23<=0.004,"Unpaid","Partial"))))
A24: 46174 | B24: P2 | C24: P2-U2 | E24: 0 | F24: =O23 | G24: =E24+F24 | N24: =SUM(IF(ISNUMBER(H24),H24,0),IF(ISNUMBER(J24),J24,0),IF(ISNUMBER(L24),L24,0)) | O24: =G24-N24 | P24: =IF(AND($D24="",E24=0,F24=0),"Vacant",IF(O24<-0.004,"Overpaid / Credit",IF(O24<=0.004,"Paid",IF(N24<=0.004,"Unpaid","Partial"))))
A25: 46204 | B25: P2 | C25: P2-U2 | D25: T4B | E25: 1100 | F25: =O24 | G25: =E25+F25 | H25: 400 | I25: 46205 | J25: 300 | K25: 46213 | L25: 300 | M25: 46225 | N25: =SUM(IF(ISNUMBER(H25),H25,0),IF(ISNUMBER(J25),J25,0),IF(ISNUMBER(L25),L25,0)) | O25: =G25-N25 | P25: =IF(AND($D25="",E25=0,F25=0),"Vacant",IF(O25<-0.004,"Overpaid / Credit",IF(O25<=0.004,"Paid",IF(N25<=0.004,"Unpaid","Partial"))))
A26: 46235 | B26: P2 | C26: P2-U2 | E26: 0 | F26: =O25 | G26: =E26+F26 | N26: =SUM(IF(ISNUMBER(H26),H26,0),IF(ISNUMBER(J26),J26,0),IF(ISNUMBER(L26),L26,0)) | O26: =G26-N26 | P26: =IF(AND($D26="",E26=0,F26=0),"Vacant",IF(O26<-0.004,"Overpaid / Credit",IF(O26<=0.004,"Paid",IF(N26<=0.004,"Unpaid","Partial"))))
A27: 46266 | B27: P2 | C27: P2-U2 | D27: T4B | E27: 1100 | F27: =O26 | G27: =E27+F27 | H27: 1100 | I27: 46268 | N27: =SUM(IF(ISNUMBER(H27),H27,0),IF(ISNUMBER(J27),J27,0),IF(ISNUMBER(L27),L27,0)) | O27: =G27-N27 | P27: =IF(AND($D27="",E27=0,F27=0),"Vacant",IF(O27<-0.004,"Overpaid / Credit",IF(O27<=0.004,"Paid",IF(N27<=0.004,"Unpaid","Partial"))))
A28: 46113 | B28: P3 | C28: P3-U1 | D28: T5 | E28: 1900 | F28: 0 | G28: =E28+F28 | H28: 1900 | I28: 46113 | N28: =SUM(IF(ISNUMBER(H28),H28,0),IF(ISNUMBER(J28),J28,0),IF(ISNUMBER(L28),L28,0)) | O28: =G28-N28 | P28: =IF(AND($D28="",E28=0,F28=0),"Vacant",IF(O28<-0.004,"Overpaid / Credit",IF(O28<=0.004,"Paid",IF(N28<=0.004,"Unpaid","Partial"))))
A29: 46143 | B29: P3 | C29: P3-U1 | D29: T5 | E29: 1900 | F29: =O28 | G29: =E29+F29 | H29: 1900 | I29: 46143 | N29: =SUM(IF(ISNUMBER(H29),H29,0),IF(ISNUMBER(J29),J29,0),IF(ISNUMBER(L29),L29,0)) | O29: =G29-N29 | P29: =IF(AND($D29="",E29=0,F29=0),"Vacant",IF(O29<-0.004,"Overpaid / Credit",IF(O29<=0.004,"Paid",IF(N29<=0.004,"Unpaid","Partial"))))
A30: 46174 | B30: P3 | C30: P3-U1 | D30: T5 | E30: 1900 | F30: =O29 | G30: =E30+F30 | H30: 1900 | I30: 46174 | N30: =SUM(IF(ISNUMBER(H30),H30,0),IF(ISNUMBER(J30),J30,0),IF(ISNUMBER(L30),L30,0)) | O30: =G30-N30 | P30: =IF(AND($D30="",E30=0,F30=0),"Vacant",IF(O30<-0.004,"Overpaid / Credit",IF(O30<=0.004,"Paid",IF(N30<=0.004,"Unpaid","Partial"))))
A31: 46204 | B31: P3 | C31: P3-U1 | D31: T5 | E31: 1900 | F31: =O30 | G31: =E31+F31 | H31: 1900 | I31: 46204 | N31: =SUM(IF(ISNUMBER(H31),H31,0),IF(ISNUMBER(J31),J31,0),IF(ISNUMBER(L31),L31,0)) | O31: =G31-N31 | P31: =IF(AND($D31="",E31=0,F31=0),"Vacant",IF(O31<-0.004,"Overpaid / Credit",IF(O31<=0.004,"Paid",IF(N31<=0.004,"Unpaid","Partial"))))
A32: 46235 | B32: P3 | C32: P3-U1 | D32: T5 | E32: 1900 | F32: =O31 | G32: =E32+F32 | H32: 1900 | I32: 46235 | N32: =SUM(IF(ISNUMBER(H32),H32,0),IF(ISNUMBER(J32),J32,0),IF(ISNUMBER(L32),L32,0)) | O32: =G32-N32 | P32: =IF(AND($D32="",E32=0,F32=0),"Vacant",IF(O32<-0.004,"Overpaid / Credit",IF(O32<=0.004,"Paid",IF(N32<=0.004,"Unpaid","Partial"))))
A33: 46266 | B33: P3 | C33: P3-U1 | D33: T5 | E33: 1900 | F33: =O32 | G33: =E33+F33 | H33: 1900 | I33: 46266 | N33: =SUM(IF(ISNUMBER(H33),H33,0),IF(ISNUMBER(J33),J33,0),IF(ISNUMBER(L33),L33,0)) | O33: =G33-N33 | P33: =IF(AND($D33="",E33=0,F33=0),"Vacant",IF(O33<-0.004,"Overpaid / Credit",IF(O33<=0.004,"Paid",IF(N33<=0.004,"Unpaid","Partial"))))
F34: 0 | G34: =E34+F34 | N34: =SUM(IF(ISNUMBER(H34),H34,0),IF(ISNUMBER(J34),J34,0),IF(ISNUMBER(L34),L34,0)) | O34: =G34-N34 | P34: =IF(AND($D34="",E34=0,F34=0),"Vacant",IF(O34<-0.004,"Overpaid / Credit",IF(O34<=0.004,"Paid",IF(N34<=0.004,"Unpaid","Partial"))))
F35: =O34 | G35: =E35+F35 | N35: =SUM(IF(ISNUMBER(H35),H35,0),IF(ISNUMBER(J35),J35,0),IF(ISNUMBER(L35),L35,0)) | O35: =G35-N35 | P35: =IF(AND($D35="",E35=0,F35=0),"Vacant",IF(O35<-0.004,"Overpaid / Credit",IF(O35<=0.004,"Paid",IF(N35<=0.004,"Unpaid","Partial"))))
F36: =O35 | G36: =E36+F36 | N36: =SUM(IF(ISNUMBER(H36),H36,0),IF(ISNUMBER(J36),J36,0),IF(ISNUMBER(L36),L36,0)) | O36: =G36-N36 | P36: =IF(AND($D36="",E36=0,F36=0),"Vacant",IF(O36<-0.004,"Overpaid / Credit",IF(O36<=0.004,"Paid",IF(N36<=0.004,"Unpaid","Partial"))))
F37: =O36 | G37: =E37+F37 | N37: =SUM(IF(ISNUMBER(H37),H37,0),IF(ISNUMBER(J37),J37,0),IF(ISNUMBER(L37),L37,0)) | O37: =G37-N37 | P37: =IF(AND($D37="",E37=0,F37=0),"Vacant",IF(O37<-0.004,"Overpaid / Credit",IF(O37<=0.004,"Paid",IF(N37<=0.004,"Unpaid","Partial"))))
F38: =O37 | G38: =E38+F38 | N38: =SUM(IF(ISNUMBER(H38),H38,0),IF(ISNUMBER(J38),J38,0),IF(ISNUMBER(L38),L38,0)) | O38: =G38-N38 | P38: =IF(AND($D38="",E38=0,F38=0),"Vacant",IF(O38<-0.004,"Overpaid / Credit",IF(O38<=0.004,"Paid",IF(N38<=0.004,"Unpaid","Partial"))))
F39: =O38 | G39: =E39+F39 | N39: =SUM(IF(ISNUMBER(H39),H39,0),IF(ISNUMBER(J39),J39,0),IF(ISNUMBER(L39),L39,0)) | O39: =G39-N39 | P39: =IF(AND($D39="",E39=0,F39=0),"Vacant",IF(O39<-0.004,"Overpaid / Credit",IF(O39<=0.004,"Paid",IF(N39<=0.004,"Unpaid","Partial"))))
F40: =O39 | G40: =E40+F40 | N40: =SUM(IF(ISNUMBER(H40),H40,0),IF(ISNUMBER(J40),J40,0),IF(ISNUMBER(L40),L40,0)) | O40: =G40-N40 | P40: =IF(AND($D40="",E40=0,F40=0),"Vacant",IF(O40<-0.004,"Overpaid / Credit",IF(O40<=0.004,"Paid",IF(N40<=0.004,"Unpaid","Partial"))))
F41: =O40 | G41: =E41+F41 | N41: =SUM(IF(ISNUMBER(H41),H41,0),IF(ISNUMBER(J41),J41,0),IF(ISNUMBER(L41),L41,0)) | O41: =G41-N41 | P41: =IF(AND($D41="",E41=0,F41=0),"Vacant",IF(O41<-0.004,"Overpaid / Credit",IF(O41<=0.004,"Paid",IF(N41<=0.004,"Unpaid","Partial"))))
F42: =O41 | G42: =E42+F42 | N42: =SUM(IF(ISNUMBER(H42),H42,0),IF(ISNUMBER(J42),J42,0),IF(ISNUMBER(L42),L42,0)) | O42: =G42-N42 | P42: =IF(AND($D42="",E42=0,F42=0),"Vacant",IF(O42<-0.004,"Overpaid / Credit",IF(O42<=0.004,"Paid",IF(N42<=0.004,"Unpaid","Partial"))))
F43: =O42 | G43: =E43+F43 | N43: =SUM(IF(ISNUMBER(H43),H43,0),IF(ISNUMBER(J43),J43,0),IF(ISNUMBER(L43),L43,0)) | O43: =G43-N43 | P43: =IF(AND($D43="",E43=0,F43=0),"Vacant",IF(O43<-0.004,"Overpaid / Credit",IF(O43<=0.004,"Paid",IF(N43<=0.004,"Unpaid","Partial"))))
F44: =O43 | G44: =E44+F44 | N44: =SUM(IF(ISNUMBER(H44),H44,0),IF(ISNUMBER(J44),J44,0),IF(ISNUMBER(L44),L44,0)) | O44: =G44-N44 | P44: =IF(AND($D44="",E44=0,F44=0),"Vacant",IF(O44<-0.004,"Overpaid / Credit",IF(O44<=0.004,"Paid",IF(N44<=0.004,"Unpaid","Partial"))))
F45: =O44 | G45: =E45+F45 | N45: =SUM(IF(ISNUMBER(H45),H45,0),IF(ISNUMBER(J45),J45,0),IF(ISNUMBER(L45),L45,0)) | O45: =G45-N45 | P45: =IF(AND($D45="",E45=0,F45=0),"Vacant",IF(O45<-0.004,"Overpaid / Credit",IF(O45<=0.004,"Paid",IF(N45<=0.004,"Unpaid","Partial"))))
F46: 0 | G46: =E46+F46 | N46: =SUM(IF(ISNUMBER(H46),H46,0),IF(ISNUMBER(J46),J46,0),IF(ISNUMBER(L46),L46,0)) | O46: =G46-N46 | P46: =IF(AND($D46="",E46=0,F46=0),"Vacant",IF(O46<-0.004,"Overpaid / Credit",IF(O46<=0.004,"Paid",IF(N46<=0.004,"Unpaid","Partial"))))
F47: =O46 | G47: =E47+F47 | N47: =SUM(IF(ISNUMBER(H47),H47,0),IF(ISNUMBER(J47),J47,0),IF(ISNUMBER(L47),L47,0)) | O47: =G47-N47 | P47: =IF(AND($D47="",E47=0,F47=0),"Vacant",IF(O47<-0.004,"Overpaid / Credit",IF(O47<=0.004,"Paid",IF(N47<=0.004,"Unpaid","Partial"))))
F48: =O47 | G48: =E48+F48 | N48: =SUM(IF(ISNUMBER(H48),H48,0),IF(ISNUMBER(J48),J48,0),IF(ISNUMBER(L48),L48,0)) | O48: =G48-N48 | P48: =IF(AND($D48="",E48=0,F48=0),"Vacant",IF(O48<-0.004,"Overpaid / Credit",IF(O48<=0.004,"Paid",IF(N48<=0.004,"Unpaid","Partial"))))
F49: =O48 | G49: =E49+F49 | N49: =SUM(IF(ISNUMBER(H49),H49,0),IF(ISNUMBER(J49),J49,0),IF(ISNUMBER(L49),L49,0)) | O49: =G49-N49 | P49: =IF(AND($D49="",E49=0,F49=0),"Vacant",IF(O49<-0.004,"Overpaid / Credit",IF(O49<=0.004,"Paid",IF(N49<=0.004,"Unpaid","Partial"))))
F50: =O49 | G50: =E50+F50 | N50: =SUM(IF(ISNUMBER(H50),H50,0),IF(ISNUMBER(J50),J50,0),IF(ISNUMBER(L50),L50,0)) | O50: =G50-N50 | P50: =IF(AND($D50="",E50=0,F50=0),"Vacant",IF(O50<-0.004,"Overpaid / Credit",IF(O50<=0.004,"Paid",IF(N50<=0.004,"Unpaid","Partial"))))
F51: =O50 | G51: =E51+F51 | N51: =SUM(IF(ISNUMBER(H51),H51,0),IF(ISNUMBER(J51),J51,0),IF(ISNUMBER(L51),L51,0)) | O51: =G51-N51 | P51: =IF(AND($D51="",E51=0,F51=0),"Vacant",IF(O51<-0.004,"Overpaid / Credit",IF(O51<=0.004,"Paid",IF(N51<=0.004,"Unpaid","Partial"))))
F52: =O51 | G52: =E52+F52 | N52: =SUM(IF(ISNUMBER(H52),H52,0),IF(ISNUMBER(J52),J52,0),IF(ISNUMBER(L52),L52,0)) | O52: =G52-N52 | P52: =IF(AND($D52="",E52=0,F52=0),"Vacant",IF(O52<-0.004,"Overpaid / Credit",IF(O52<=0.004,"Paid",IF(N52<=0.004,"Unpaid","Partial"))))
F53: =O52 | G53: =E53+F53 | N53: =SUM(IF(ISNUMBER(H53),H53,0),IF(ISNUMBER(J53),J53,0),IF(ISNUMBER(L53),L53,0)) | O53: =G53-N53 | P53: =IF(AND($D53="",E53=0,F53=0),"Vacant",IF(O53<-0.004,"Overpaid / Credit",IF(O53<=0.004,"Paid",IF(N53<=0.004,"Unpaid","Partial"))))
F54: =O53 | G54: =E54+F54 | N54: =SUM(IF(ISNUMBER(H54),H54,0),IF(ISNUMBER(J54),J54,0),IF(ISNUMBER(L54),L54,0)) | O54: =G54-N54 | P54: =IF(AND($D54="",E54=0,F54=0),"Vacant",IF(O54<-0.004,"Overpaid / Credit",IF(O54<=0.004,"Paid",IF(N54<=0.004,"Unpaid","Partial"))))
F55: =O54 | G55: =E55+F55 | N55: =SUM(IF(ISNUMBER(H55),H55,0),IF(ISNUMBER(J55),J55,0),IF(ISNUMBER(L55),L55,0)) | O55: =G55-N55 | P55: =IF(AND($D55="",E55=0,F55=0),"Vacant",IF(O55<-0.004,"Overpaid / Credit",IF(O55<=0.004,"Paid",IF(N55<=0.004,"Unpaid","Partial"))))
F56: =O55 | G56: =E56+F56 | N56: =SUM(IF(ISNUMBER(H56),H56,0),IF(ISNUMBER(J56),J56,0),IF(ISNUMBER(L56),L56,0)) | O56: =G56-N56 | P56: =IF(AND($D56="",E56=0,F56=0),"Vacant",IF(O56<-0.004,"Overpaid / Credit",IF(O56<=0.004,"Paid",IF(N56<=0.004,"Unpaid","Partial"))))
F57: =O56 | G57: =E57+F57 | N57: =SUM(IF(ISNUMBER(H57),H57,0),IF(ISNUMBER(J57),J57,0),IF(ISNUMBER(L57),L57,0)) | O57: =G57-N57 | P57: =IF(AND($D57="",E57=0,F57=0),"Vacant",IF(O57<-0.004,"Overpaid / Credit",IF(O57<=0.004,"Paid",IF(N57<=0.004,"Unpaid","Partial"))))
F58: 0 | G58: =E58+F58 | N58: =SUM(IF(ISNUMBER(H58),H58,0),IF(ISNUMBER(J58),J58,0),IF(ISNUMBER(L58),L58,0)) | O58: =G58-N58 | P58: =IF(AND($D58="",E58=0,F58=0),"Vacant",IF(O58<-0.004,"Overpaid / Credit",IF(O58<=0.004,"Paid",IF(N58<=0.004,"Unpaid","Partial"))))
F59: =O58 | G59: =E59+F59 | N59: =SUM(IF(ISNUMBER(H59),H59,0),IF(ISNUMBER(J59),J59,0),IF(ISNUMBER(L59),L59,0)) | O59: =G59-N59 | P59: =IF(AND($D59="",E59=0,F59=0),"Vacant",IF(O59<-0.004,"Overpaid / Credit",IF(O59<=0.004,"Paid",IF(N59<=0.004,"Unpaid","Partial"))))
F60: =O59 | G60: =E60+F60 | N60: =SUM(IF(ISNUMBER(H60),H60,0),IF(ISNUMBER(J60),J60,0),IF(ISNUMBER(L60),L60,0)) | O60: =G60-N60 | P60: =IF(AND($D60="",E60=0,F60=0),"Vacant",IF(O60<-0.004,"Overpaid / Credit",IF(O60<=0.004,"Paid",IF(N60<=0.004,"Unpaid","Partial"))))
F61: =O60 | G61: =E61+F61 | N61: =SUM(IF(ISNUMBER(H61),H61,0),IF(ISNUMBER(J61),J61,0),IF(ISNUMBER(L61),L61,0)) | O61: =G61-N61 | P61: =IF(AND($D61="",E61=0,F61=0),"Vacant",IF(O61<-0.004,"Overpaid / Credit",IF(O61<=0.004,"Paid",IF(N61<=0.004,"Unpaid","Partial"))))
F62: =O61 | G62: =E62+F62 | N62: =SUM(IF(ISNUMBER(H62),H62,0),IF(ISNUMBER(J62),J62,0),IF(ISNUMBER(L62),L62,0)) | O62: =G62-N62 | P62: =IF(AND($D62="",E62=0,F62=0),"Vacant",IF(O62<-0.004,"Overpaid / Credit",IF(O62<=0.004,"Paid",IF(N62<=0.004,"Unpaid","Partial"))))
F63: =O62 | G63: =E63+F63 | N63: =SUM(IF(ISNUMBER(H63),H63,0),IF(ISNUMBER(J63),J63,0),IF(ISNUMBER(L63),L63,0)) | O63: =G63-N63 | P63: =IF(AND($D63="",E63=0,F63=0),"Vacant",IF(O63<-0.004,"Overpaid / Credit",IF(O63<=0.004,"Paid",IF(N63<=0.004,"Unpaid","Partial"))))
F64: =O63 | G64: =E64+F64 | N64: =SUM(IF(ISNUMBER(H64),H64,0),IF(ISNUMBER(J64),J64,0),IF(ISNUMBER(L64),L64,0)) | O64: =G64-N64 | P64: =IF(AND($D64="",E64=0,F64=0),"Vacant",IF(O64<-0.004,"Overpaid / Credit",IF(O64<=0.004,"Paid",IF(N64<=0.004,"Unpaid","Partial"))))
F65: =O64 | G65: =E65+F65 | N65: =SUM(IF(ISNUMBER(H65),H65,0),IF(ISNUMBER(J65),J65,0),IF(ISNUMBER(L65),L65,0)) | O65: =G65-N65 | P65: =IF(AND($D65="",E65=0,F65=0),"Vacant",IF(O65<-0.004,"Overpaid / Credit",IF(O65<=0.004,"Paid",IF(N65<=0.004,"Unpaid","Partial"))))
F66: =O65 | G66: =E66+F66 | N66: =SUM(IF(ISNUMBER(H66),H66,0),IF(ISNUMBER(J66),J66,0),IF(ISNUMBER(L66),L66,0)) | O66: =G66-N66 | P66: =IF(AND($D66="",E66=0,F66=0),"Vacant",IF(O66<-0.004,"Overpaid / Credit",IF(O66<=0.004,"Paid",IF(N66<=0.004,"Unpaid","Partial"))))
F67: =O66 | G67: =E67+F67 | N67: =SUM(IF(ISNUMBER(H67),H67,0),IF(ISNUMBER(J67),J67,0),IF(ISNUMBER(L67),L67,0)) | O67: =G67-N67 | P67: =IF(AND($D67="",E67=0,F67=0),"Vacant",IF(O67<-0.004,"Overpaid / Credit",IF(O67<=0.004,"Paid",IF(N67<=0.004,"Unpaid","Partial"))))
F68: =O67 | G68: =E68+F68 | N68: =SUM(IF(ISNUMBER(H68),H68,0),IF(ISNUMBER(J68),J68,0),IF(ISNUMBER(L68),L68,0)) | O68: =G68-N68 | P68: =IF(AND($D68="",E68=0,F68=0),"Vacant",IF(O68<-0.004,"Overpaid / Credit",IF(O68<=0.004,"Paid",IF(N68<=0.004,"Unpaid","Partial"))))
F69: =O68 | G69: =E69+F69 | N69: =SUM(IF(ISNUMBER(H69),H69,0),IF(ISNUMBER(J69),J69,0),IF(ISNUMBER(L69),L69,0)) | O69: =G69-N69 | P69: =IF(AND($D69="",E69=0,F69=0),"Vacant",IF(O69<-0.004,"Overpaid / Credit",IF(O69<=0.004,"Paid",IF(N69<=0.004,"Unpaid","Partial"))))
F70: 0 | G70: =E70+F70 | N70: =SUM(IF(ISNUMBER(H70),H70,0),IF(ISNUMBER(J70),J70,0),IF(ISNUMBER(L70),L70,0)) | O70: =G70-N70 | P70: =IF(AND($D70="",E70=0,F70=0),"Vacant",IF(O70<-0.004,"Overpaid / Credit",IF(O70<=0.004,"Paid",IF(N70<=0.004,"Unpaid","Partial"))))
F71: =O70 | G71: =E71+F71 | N71: =SUM(IF(ISNUMBER(H71),H71,0),IF(ISNUMBER(J71),J71,0),IF(ISNUMBER(L71),L71,0)) | O71: =G71-N71 | P71: =IF(AND($D71="",E71=0,F71=0),"Vacant",IF(O71<-0.004,"Overpaid / Credit",IF(O71<=0.004,"Paid",IF(N71<=0.004,"Unpaid","Partial"))))
F72: =O71 | G72: =E72+F72 | N72: =SUM(IF(ISNUMBER(H72),H72,0),IF(ISNUMBER(J72),J72,0),IF(ISNUMBER(L72),L72,0)) | O72: =G72-N72 | P72: =IF(AND($D72="",E72=0,F72=0),"Vacant",IF(O72<-0.004,"Overpaid / Credit",IF(O72<=0.004,"Paid",IF(N72<=0.004,"Unpaid","Partial"))))
F73: =O72 | G73: =E73+F73 | N73: =SUM(IF(ISNUMBER(H73),H73,0),IF(ISNUMBER(J73),J73,0),IF(ISNUMBER(L73),L73,0)) | O73: =G73-N73 | P73: =IF(AND($D73="",E73=0,F73=0),"Vacant",IF(O73<-0.004,"Overpaid / Credit",IF(O73<=0.004,"Paid",IF(N73<=0.004,"Unpaid","Partial"))))
F74: =O73 | G74: =E74+F74 | N74: =SUM(IF(ISNUMBER(H74),H74,0),IF(ISNUMBER(J74),J74,0),IF(ISNUMBER(L74),L74,0)) | O74: =G74-N74 | P74: =IF(AND($D74="",E74=0,F74=0),"Vacant",IF(O74<-0.004,"Overpaid / Credit",IF(O74<=0.004,"Paid",IF(N74<=0.004,"Unpaid","Partial"))))
F75: =O74 | G75: =E75+F75 | N75: =SUM(IF(ISNUMBER(H75),H75,0),IF(ISNUMBER(J75),J75,0),IF(ISNUMBER(L75),L75,0)) | O75: =G75-N75 | P75: =IF(AND($D75="",E75=0,F75=0),"Vacant",IF(O75<-0.004,"Overpaid / Credit",IF(O75<=0.004,"Paid",IF(N75<=0.004,"Unpaid","Partial"))))
F76: =O75 | G76: =E76+F76 | N76: =SUM(IF(ISNUMBER(H76),H76,0),IF(ISNUMBER(J76),J76,0),IF(ISNUMBER(L76),L76,0)) | O76: =G76-N76 | P76: =IF(AND($D76="",E76=0,F76=0),"Vacant",IF(O76<-0.004,"Overpaid / Credit",IF(O76<=0.004,"Paid",IF(N76<=0.004,"Unpaid","Partial"))))
F77: =O76 | G77: =E77+F77 | N77: =SUM(IF(ISNUMBER(H77),H77,0),IF(ISNUMBER(J77),J77,0),IF(ISNUMBER(L77),L77,0)) | O77: =G77-N77 | P77: =IF(AND($D77="",E77=0,F77=0),"Vacant",IF(O77<-0.004,"Overpaid / Credit",IF(O77<=0.004,"Paid",IF(N77<=0.004,"Unpaid","Partial"))))
F78: =O77 | G78: =E78+F78 | N78: =SUM(IF(ISNUMBER(H78),H78,0),IF(ISNUMBER(J78),J78,0),IF(ISNUMBER(L78),L78,0)) | O78: =G78-N78 | P78: =IF(AND($D78="",E78=0,F78=0),"Vacant",IF(O78<-0.004,"Overpaid / Credit",IF(O78<=0.004,"Paid",IF(N78<=0.004,"Unpaid","Partial"))))
F79: =O78 | G79: =E79+F79 | N79: =SUM(IF(ISNUMBER(H79),H79,0),IF(ISNUMBER(J79),J79,0),IF(ISNUMBER(L79),L79,0)) | O79: =G79-N79 | P79: =IF(AND($D79="",E79=0,F79=0),"Vacant",IF(O79<-0.004,"Overpaid / Credit",IF(O79<=0.004,"Paid",IF(N79<=0.004,"Unpaid","Partial"))))
F80: =O79 | G80: =E80+F80 | N80: =SUM(IF(ISNUMBER(H80),H80,0),IF(ISNUMBER(J80),J80,0),IF(ISNUMBER(L80),L80,0)) | O80: =G80-N80 | P80: =IF(AND($D80="",E80=0,F80=0),"Vacant",IF(O80<-0.004,"Overpaid / Credit",IF(O80<=0.004,"Paid",IF(N80<=0.004,"Unpaid","Partial"))))
F81: =O80 | G81: =E81+F81 | N81: =SUM(IF(ISNUMBER(H81),H81,0),IF(ISNUMBER(J81),J81,0),IF(ISNUMBER(L81),L81,0)) | O81: =G81-N81 | P81: =IF(AND($D81="",E81=0,F81=0),"Vacant",IF(O81<-0.004,"Overpaid / Credit",IF(O81<=0.004,"Paid",IF(N81<=0.004,"Unpaid","Partial"))))
F82: 0 | G82: =E82+F82 | N82: =SUM(IF(ISNUMBER(H82),H82,0),IF(ISNUMBER(J82),J82,0),IF(ISNUMBER(L82),L82,0)) | O82: =G82-N82 | P82: =IF(AND($D82="",E82=0,F82=0),"Vacant",IF(O82<-0.004,"Overpaid / Credit",IF(O82<=0.004,"Paid",IF(N82<=0.004,"Unpaid","Partial"))))
F83: =O82 | G83: =E83+F83 | N83: =SUM(IF(ISNUMBER(H83),H83,0),IF(ISNUMBER(J83),J83,0),IF(ISNUMBER(L83),L83,0)) | O83: =G83-N83 | P83: =IF(AND($D83="",E83=0,F83=0),"Vacant",IF(O83<-0.004,"Overpaid / Credit",IF(O83<=0.004,"Paid",IF(N83<=0.004,"Unpaid","Partial"))))
F84: =O83 | G84: =E84+F84 | N84: =SUM(IF(ISNUMBER(H84),H84,0),IF(ISNUMBER(J84),J84,0),IF(ISNUMBER(L84),L84,0)) | O84: =G84-N84 | P84: =IF(AND($D84="",E84=0,F84=0),"Vacant",IF(O84<-0.004,"Overpaid / Credit",IF(O84<=0.004,"Paid",IF(N84<=0.004,"Unpaid","Partial"))))
F85: =O84 | G85: =E85+F85 | N85: =SUM(IF(ISNUMBER(H85),H85,0),IF(ISNUMBER(J85),J85,0),IF(ISNUMBER(L85),L85,0)) | O85: =G85-N85 | P85: =IF(AND($D85="",E85=0,F85=0),"Vacant",IF(O85<-0.004,"Overpaid / Credit",IF(O85<=0.004,"Paid",IF(N85<=0.004,"Unpaid","Partial"))))
F86: =O85 | G86: =E86+F86 | N86: =SUM(IF(ISNUMBER(H86),H86,0),IF(ISNUMBER(J86),J86,0),IF(ISNUMBER(L86),L86,0)) | O86: =G86-N86 | P86: =IF(AND($D86="",E86=0,F86=0),"Vacant",IF(O86<-0.004,"Overpaid / Credit",IF(O86<=0.004,"Paid",IF(N86<=0.004,"Unpaid","Partial"))))
F87: =O86 | G87: =E87+F87 | N87: =SUM(IF(ISNUMBER(H87),H87,0),IF(ISNUMBER(J87),J87,0),IF(ISNUMBER(L87),L87,0)) | O87: =G87-N87 | P87: =IF(AND($D87="",E87=0,F87=0),"Vacant",IF(O87<-0.004,"Overpaid / Credit",IF(O87<=0.004,"Paid",IF(N87<=0.004,"Unpaid","Partial"))))
F88: =O87 | G88: =E88+F88 | N88: =SUM(IF(ISNUMBER(H88),H88,0),IF(ISNUMBER(J88),J88,0),IF(ISNUMBER(L88),L88,0)) | O88: =G88-N88 | P88: =IF(AND($D88="",E88=0,F88=0),"Vacant",IF(O88<-0.004,"Overpaid / Credit",IF(O88<=0.004,"Paid",IF(N88<=0.004,"Unpaid","Partial"))))
F89: =O88 | G89: =E89+F89 | N89: =SUM(IF(ISNUMBER(H89),H89,0),IF(ISNUMBER(J89),J89,0),IF(ISNUMBER(L89),L89,0)) | O89: =G89-N89 | P89: =IF(AND($D89="",E89=0,F89=0),"Vacant",IF(O89<-0.004,"Overpaid / Credit",IF(O89<=0.004,"Paid",IF(N89<=0.004,"Unpaid","Partial"))))
F90: =O89 | G90: =E90+F90 | N90: =SUM(IF(ISNUMBER(H90),H90,0),IF(ISNUMBER(J90),J90,0),IF(ISNUMBER(L90),L90,0)) | O90: =G90-N90 | P90: =IF(AND($D90="",E90=0,F90=0),"Vacant",IF(O90<-0.004,"Overpaid / Credit",IF(O90<=0.004,"Paid",IF(N90<=0.004,"Unpaid","Partial"))))
F91: =O90 | G91: =E91+F91 | N91: =SUM(IF(ISNUMBER(H91),H91,0),IF(ISNUMBER(J91),J91,0),IF(ISNUMBER(L91),L91,0)) | O91: =G91-N91 | P91: =IF(AND($D91="",E91=0,F91=0),"Vacant",IF(O91<-0.004,"Overpaid / Credit",IF(O91<=0.004,"Paid",IF(N91<=0.004,"Unpaid","Partial"))))
F92: =O91 | G92: =E92+F92 | N92: =SUM(IF(ISNUMBER(H92),H92,0),IF(ISNUMBER(J92),J92,0),IF(ISNUMBER(L92),L92,0)) | O92: =G92-N92 | P92: =IF(AND($D92="",E92=0,F92=0),"Vacant",IF(O92<-0.004,"Overpaid / Credit",IF(O92<=0.004,"Paid",IF(N92<=0.004,"Unpaid","Partial"))))
F93: =O92 | G93: =E93+F93 | N93: =SUM(IF(ISNUMBER(H93),H93,0),IF(ISNUMBER(J93),J93,0),IF(ISNUMBER(L93),L93,0)) | O93: =G93-N93 | P93: =IF(AND($D93="",E93=0,F93=0),"Vacant",IF(O93<-0.004,"Overpaid / Credit",IF(O93<=0.004,"Paid",IF(N93<=0.004,"Unpaid","Partial"))))
F94: 0 | G94: =E94+F94 | N94: =SUM(IF(ISNUMBER(H94),H94,0),IF(ISNUMBER(J94),J94,0),IF(ISNUMBER(L94),L94,0)) | O94: =G94-N94 | P94: =IF(AND($D94="",E94=0,F94=0),"Vacant",IF(O94<-0.004,"Overpaid / Credit",IF(O94<=0.004,"Paid",IF(N94<=0.004,"Unpaid","Partial"))))
F95: =O94 | G95: =E95+F95 | N95: =SUM(IF(ISNUMBER(H95),H95,0),IF(ISNUMBER(J95),J95,0),IF(ISNUMBER(L95),L95,0)) | O95: =G95-N95 | P95: =IF(AND($D95="",E95=0,F95=0),"Vacant",IF(O95<-0.004,"Overpaid / Credit",IF(O95<=0.004,"Paid",IF(N95<=0.004,"Unpaid","Partial"))))
F96: =O95 | G96: =E96+F96 | N96: =SUM(IF(ISNUMBER(H96),H96,0),IF(ISNUMBER(J96),J96,0),IF(ISNUMBER(L96),L96,0)) | O96: =G96-N96 | P96: =IF(AND($D96="",E96=0,F96=0),"Vacant",IF(O96<-0.004,"Overpaid / Credit",IF(O96<=0.004,"Paid",IF(N96<=0.004,"Unpaid","Partial"))))
F97: =O96 | G97: =E97+F97 | N97: =SUM(IF(ISNUMBER(H97),H97,0),IF(ISNUMBER(J97),J97,0),IF(ISNUMBER(L97),L97,0)) | O97: =G97-N97 | P97: =IF(AND($D97="",E97=0,F97=0),"Vacant",IF(O97<-0.004,"Overpaid / Credit",IF(O97<=0.004,"Paid",IF(N97<=0.004,"Unpaid","Partial"))))
F98: =O97 | G98: =E98+F98 | N98: =SUM(IF(ISNUMBER(H98),H98,0),IF(ISNUMBER(J98),J98,0),IF(ISNUMBER(L98),L98,0)) | O98: =G98-N98 | P98: =IF(AND($D98="",E98=0,F98=0),"Vacant",IF(O98<-0.004,"Overpaid / Credit",IF(O98<=0.004,"Paid",IF(N98<=0.004,"Unpaid","Partial"))))
F99: =O98 | G99: =E99+F99 | N99: =SUM(IF(ISNUMBER(H99),H99,0),IF(ISNUMBER(J99),J99,0),IF(ISNUMBER(L99),L99,0)) | O99: =G99-N99 | P99: =IF(AND($D99="",E99=0,F99=0),"Vacant",IF(O99<-0.004,"Overpaid / Credit",IF(O99<=0.004,"Paid",IF(N99<=0.004,"Unpaid","Partial"))))
F100: =O99 | G100: =E100+F100 | N100: =SUM(IF(ISNUMBER(H100),H100,0),IF(ISNUMBER(J100),J100,0),IF(ISNUMBER(L100),L100,0)) | O100: =G100-N100 | P100: =IF(AND($D100="",E100=0,F100=0),"Vacant",IF(O100<-0.004,"Overpaid / Credit",IF(O100<=0.004,"Paid",IF(N100<=0.004,"Unpaid","Partial"))))
...

Sheet Income & Expenses
A1: INCOME & EXPENSES
A3: Date | B3: Property | C3: Unit | D3: Type | E3: Category | F3: Description | G3: Amount | H3: Vendor / Source | I3: Payment Method | J3: Receipt / Document Link | K3: Tax/Year-End Category | L3: Notes
A4: 46117 | B4: P1 | C4: P1-U1 | D4: Income | E4: Rent | F4: April rent | G4: 1500 | I4: Bank Transfer | K4: Rental Income
A5: 46122 | B5: P1 | C5: P1-U1 | D5: Expense | E5: Repairs | F5: Leaky faucet repair | G5: 145 | H5: Springfield Plumbing | I5: Card | K5: Repairs
A6: 46127 | B6: P2 | C6: P2-U1 | D6: Expense | E6: Insurance | F6: Annual property insurance (prorated) | G6: 210 | H6: SafeHome Insurance | I6: Bank Transfer | K6: Insurance
A7: 46132 | B7: P1 | D7: Expense | E7: Property Tax | F7: Q2 property tax, Maple Ave | G7: 620 | H7: County Treasurer | I7: Bank Transfer | K7: Property Tax
A8: 46145 | B8: P3 | C8: P3-U1 | D8: Income | E8: Late Fee | F8: Late fee (paid on time, not applied) | G8: 0 | K8: Other Income
A9: 46150 | B9: P2 | C9: P2-U1 | D9: Expense | E9: Utilities | F9: Common-area electric | G9: 88 | H9: City Power Co | I9: Card | K9: Utilities
A10: 46160 | B10: P1 | C10: P1-U2 | D10: Expense | E10: Cleaning | F10: Turnover cleaning after T2 moved out | G10: 180 | H10: SparkleClean Co | I10: Card | K10: Cleaning
A11: 46175 | B11: P3 | C11: P3-U1 | D11: Expense | E11: HOA | F11: Monthly HOA dues | G11: 45 | H11: Elm Court HOA | I11: Bank Transfer | K11: HOA
A12: 46185 | B12: P2 | C12: P2-U2 | D12: Expense | E12: Advertising | F12: Listing ad for vacant unit | G12: 35 | H12: RentBoard.com | I12: Card | K12: Advertising
A13: 46204 | B13: P1 | C13: P1-U2 | D13: Income | E13: Rent | F13: First month rent, new tenant Aisha Bello | G13: 1250 | I13: Bank Transfer | K13: Rental Income
A14: 46212 | B14: P1 | D14: Expense | E14: Management Fees | F14: Property management, Maple Ave | G14: 150 | H14: Springfield PM Co | I14: Bank Transfer | K14: Management Fees
A15: 46248 | B15: P3 | C15: P3-U1 | D15: Expense | E15: Legal/Professional | F15: Lease renewal document review | G15: 120 | H15: Hart & Kim LLP | I15: Card | K15: Legal/Professional
A16: 46266 | B16: P2 | C16: P2-U2 | D16: Income | E16: Rent | F16: First month rent, new tenant Marcus Webb | G16: 1100 | I16: Bank Transfer | K16: Rental Income
A33: TOTAL INCOME | G33: =SUMIF(D4:D31,"Income",G4:G31)
A34: TOTAL EXPENSES | G34: =SUMIF(D4:D31,"Expense",G4:G31)
A35: NET | G35: =G33-G34

Sheet Maintenance & Repairs
A1: MAINTENANCE & REPAIRS
A3: Request ID | B3: Date Reported | C3: Property | D3: Unit | E3: Issue | F3: Priority | G3: Status | H3: Vendor | I3: Estimated Cost | J3: Actual Cost | K3: Scheduled Date | L3: Completed Date | M3: Notes
A4: M1 | B4: 46120 | C4: P1 | D4: P1-U1 | E4: Kitchen faucet leaking | F4: Medium | G4: Completed | H4: Springfield Plumbing | I4: 150 | J4: 145 | K4: 46122 | L4: 46122
A5: M2 | B5: 46162 | C5: P1 | D5: P1-U2 | E5: Turnover cleaning + paint touch-up | F5: Low | G5: Completed | H5: SparkleClean Co | I5: 200 | J5: 180 | K5: 46164 | L5: 46164
A6: M3 | B6: 46178 | C6: P2 | D6: P2-U1 | E6: AC unit making noise | F6: High | G6: Scheduled | H6: CoolAir HVAC | I6: 300 | K6: 46290
A7: M4 | B7: 46235 | C7: P3 | D7: P3-U1 | E7: Gutter cleaning before fall | F7: Low | G7: Open | I7: 120
A8: M5 | B8: 46270 | C8: P2 | D8: P2-U2 | E8: Replace broken window latch (move-in prep) | F8: Medium | G8: Waiting | H8: GlassFix Co | I8: 90
A10: Open Maintenance Count | B10: =COUNTIF(G4:G18,"Open")+COUNTIF(G4:G18,"Scheduled")+COUNTIF(G4:G18,"Waiting")
A11: Urgent/High Priority Open Count | B11: =SUMPRODUCT((F4:F18="High")*(G4:G18<>"Completed")*(G4:G18<>"Cancelled"))+SUMPRODUCT((F4:F18="Urgent")*(G4:G18<>"Completed")*(G4:G18<>"Cancelled"))
A12: This Month's Completed Spend | B12: =SUMPRODUCT((TEXT(L4:L18,"yyyy-mm")=TEXT(TODAY(),"yyyy-mm"))*IF(ISNUMBER(J4:J18),J4:J18,0))

Sheet Deposits & Capital Improvements
A1: SECTION A — SECURITY DEPOSITS
A3: Property | B3: Unit | C3: Tenant | D3: Deposit Required | E3: Deposit Received | F3: Date Received | G3: Deductions | H3: Amount Returned | I3: Date Returned
A4: P1 | B4: P1-U1 | C4: John Smith | D4: 1500 | E4: 1500 | F4: 45658 | G4: 0
A5: P1 | B5: P1-U2 | C5: Maria Lopez | D5: 1200 | E5: 1200 | F5: 45689 | G5: 100 | H5: 1100 | I5: 46208
A6: P1 | B6: P1-U2 | C6: Aisha Bello | D6: 1250 | E6: 1250 | F6: 46204 | G6: 0
A7: P2 | B7: P2-U1 | C7: David Chen | D7: 1200 | E7: 1200 | F7: 45383 | G7: 0
A8: P2 | B8: P2-U2 | C8: Marcus Webb | D8: 1100 | E8: 1100 | F8: 46266 | G8: 0
A9: P3 | B9: P3-U1 | C9: Priya Patel | D9: 1900 | E9: 1900 | F9: 45901 | G9: 0
A11: Total Deposits Held (Received minus Returned) | E11: =SUM(E4:E9)-SUM(H4:H9)
A14: SECTION B — CAPITAL IMPROVEMENTS
A16: Date | B16: Property | C16: Unit | D16: Improvement | E16: Vendor | F16: Cost | G16: Category
A17: 46143 | B17: P2 | C17: P2-U1 | D17: New water heater | E17: Springfield Plumbing | F17: 950 | G17: Appliance
A18: 46223 | B18: P1 | C18: P1-U2 | D18: Refinished hardwood floors (turnover) | E18: FloorCraft Co | F18: 1400 | G18: Flooring
A20: Total Capital Improvements | F20: =SUM(F17:F18)
A22: This is an organizational ledger only — it does not calculate depreciation or state any tax treatment.

Sheet Dashboard
A1: PORTFOLIO DASHBOARD
A3: Properties | B3: =SUMPRODUCT(('Properties & Units'!$A$4:$A$38<>"")/COUNTIF('Properties & Units'!$A$4:$A$38,'Properties & Units'!$A$4:$A$38&""))
A4: Occupied Units | B4: =COUNTIF('Properties & Units'!$J$4:$J$38,"Occupied")
A5: Monthly Rent Due (this sheet total) | B5: ='Rent Tracker'!$B$337
A6: Rent Collected (this sheet total) | B6: ='Rent Tracker'!$B$338
A7: Outstanding Rent (this sheet total) | B7: ='Rent Tracker'!$B$339
A8: Income YTD | B8: ='Income & Expenses'!$G$33
A9: Expenses YTD | B9: ='Income & Expenses'!$G$34
A10: Net Cash Flow YTD | B10: ='Income & Expenses'!$G$35
A11: Open Maintenance | B11: ='Maintenance & Repairs'!$B$10
A12: Deposits Held | B12: ='Deposits & Capital Improvements'!$E$11
A14: ACTION ITEMS
A15: Overdue / Partial Rent (count) | B15: ='Rent Tracker'!$B$340
A16: Leases Expiring / Expired (flag count) | B16: =SUMPRODUCT(('Tenants & Leases'!$M$4:$M$38<>"")*1)
A17: Open Maintenance (count) | B17: ='Maintenance & Repairs'!$B$10
A18: Vacant Units (count) | B18: =COUNTIF('Properties & Units'!$J$4:$J$38,"Vacant")
A90: CHART DATA (auto-calculated from the sheets above — do not edit)
A92: Month | B92: Income | C92: Expenses
A93: 46113 | B93: =SUMPRODUCT((YEAR('Income & Expenses'!$A$4:$A$31)=2026)*(MONTH('Income & Expenses'!$A$4:$A$31)=4)*('Income & Expenses'!$D$4:$D$31="Income")*'Income & Expenses'!$G$4:$G$31) | C93: =SUMPRODUCT((YEAR('Income & Expenses'!$A$4:$A$31)=2026)*(MONTH('Income & Expenses'!$A$4:$A$31)=4)*('Income & Expenses'!$D$4:$D$31="Expense")*'Income & Expenses'!$G$4:$G$31)
A94: 46143 | B94: =SUMPRODUCT((YEAR('Income & Expenses'!$A$4:$A$31)=2026)*(MONTH('Income & Expenses'!$A$4:$A$31)=5)*('Income & Expenses'!$D$4:$D$31="Income")*'Income & Expenses'!$G$4:$G$31) | C94: =SUMPRODUCT((YEAR('Income & Expenses'!$A$4:$A$31)=2026)*(MONTH('Income & Expenses'!$A$4:$A$31)=5)*('Income & Expenses'!$D$4:$D$31="Expense")*'Income & Expenses'!$G$4:$G$31)
A95: 46174 | B95: =SUMPRODUCT((YEAR('Income & Expenses'!$A$4:$A$31)=2026)*(MONTH('Income & Expenses'!$A$4:$A$31)=6)*('Income & Expenses'!$D$4:$D$31="Income")*'Income & Expenses'!$G$4:$G$31) | C95: =SUMPRODUCT((YEAR('Income & Expenses'!$A$4:$A$31)=2026)*(MONTH('Income & Expenses'!$A$4:$A$31)=6)*('Income & Expenses'!$D$4:$D$31="Expense")*'Income & Expenses'!$G$4:$G$31)
A96: 46204 | B96: =SUMPRODUCT((YEAR('Income & Expenses'!$A$4:$A$31)=2026)*(MONTH('Income & Expenses'!$A$4:$A$31)=7)*('Income & Expenses'!$D$4:$D$31="Income")*'Income & Expenses'!$G$4:$G$31) | C96: =SUMPRODUCT((YEAR('Income & Expenses'!$A$4:$A$31)=2026)*(MONTH('Income & Expenses'!$A$4:$A$31)=7)*('Income & Expenses'!$D$4:$D$31="Expense")*'Income & Expenses'!$G$4:$G$31)
A97: 46235 | B97: =SUMPRODUCT((YEAR('Income & Expenses'!$A$4:$A$31)=2026)*(MONTH('Income & Expenses'!$A$4:$A$31)=8)*('Income & Expenses'!$D$4:$D$31="Income")*'Income & Expenses'!$G$4:$G$31) | C97: =SUMPRODUCT((YEAR('Income & Expenses'!$A$4:$A$31)=2026)*(MONTH('Income & Expenses'!$A$4:$A$31)=8)*('Income & Expenses'!$D$4:$D$31="Expense")*'Income & Expenses'!$G$4:$G$31)
A98: 46266 | B98: =SUMPRODUCT((YEAR('Income & Expenses'!$A$4:$A$31)=2026)*(MONTH('Income & Expenses'!$A$4:$A$31)=9)*('Income & Expenses'!$D$4:$D$31="Income")*'Income & Expenses'!$G$4:$G$31) | C98: =SUMPRODUCT((YEAR('Income & Expenses'!$A$4:$A$31)=2026)*(MONTH('Income & Expenses'!$A$4:$A$31)=9)*('Income & Expenses'!$D$4:$D$31="Expense")*'Income & Expenses'!$G$4:$G$31)
A101: Month | B101: Rent Due | C101: Rent Collected
A102: 46113 | B102: =SUMPRODUCT((YEAR('Rent Tracker'!$A$4:$A$333)=2026)*(MONTH('Rent Tracker'!$A$4:$A$333)=4)*'Rent Tracker'!$G$4:$G$333) | C102: =SUMPRODUCT((YEAR('Rent Tracker'!$A$4:$A$333)=2026)*(MONTH('Rent Tracker'!$A$4:$A$333)=4)*'Rent Tracker'!$N$4:$N$333)
A103: 46143 | B103: =SUMPRODUCT((YEAR('Rent Tracker'!$A$4:$A$333)=2026)*(MONTH('Rent Tracker'!$A$4:$A$333)=5)*'Rent Tracker'!$G$4:$G$333) | C103: =SUMPRODUCT((YEAR('Rent Tracker'!$A$4:$A$333)=2026)*(MONTH('Rent Tracker'!$A$4:$A$333)=5)*'Rent Tracker'!$N$4:$N$333)
A104: 46174 | B104: =SUMPRODUCT((YEAR('Rent Tracker'!$A$4:$A$333)=2026)*(MONTH('Rent Tracker'!$A$4:$A$333)=6)*'Rent Tracker'!$G$4:$G$333) | C104: =SUMPRODUCT((YEAR('Rent Tracker'!$A$4:$A$333)=2026)*(MONTH('Rent Tracker'!$A$4:$A$333)=6)*'Rent Tracker'!$N$4:$N$333)
A105: 46204 | B105: =SUMPRODUCT((YEAR('Rent Tracker'!$A$4:$A$333)=2026)*(MONTH('Rent Tracker'!$A$4:$A$333)=7)*'Rent Tracker'!$G$4:$G$333) | C105: =SUMPRODUCT((YEAR('Rent Tracker'!$A$4:$A$333)=2026)*(MONTH('Rent Tracker'!$A$4:$A$333)=7)*'Rent Tracker'!$N$4:$N$333)
A106: 46235 | B106: =SUMPRODUCT((YEAR('Rent Tracker'!$A$4:$A$333)=2026)*(MONTH('Rent Tracker'!$A$4:$A$333)=8)*'Rent Tracker'!$G$4:$G$333) | C106: =SUMPRODUCT((YEAR('Rent Tracker'!$A$4:$A$333)=2026)*(MONTH('Rent Tracker'!$A$4:$A$333)=8)*'Rent Tracker'!$N$4:$N$333)
A107: 46266 | B107: =SUMPRODUCT((YEAR('Rent Tracker'!$A$4:$A$333)=2026)*(MONTH('Rent Tracker'!$A$4:$A$333)=9)*'Rent Tracker'!$G$4:$G$333) | C107: =SUMPRODUCT((YEAR('Rent Tracker'!$A$4:$A$333)=2026)*(MONTH('Rent Tracker'!$A$4:$A$333)=9)*'Rent Tracker'!$N$4:$N$333)

Sheet Year-End Summary
A1: YEAR-END SUMMARY
A2: Designed to help organize records for year-end review.
A4: Total Rental Income | B4: =SUMIF('Income & Expenses'!$D$4:$D$31,"Income",'Income & Expenses'!$G$4:$G$31)
A5: Other Income | B5: =0
A6: Total Expenses | B6: ='Income & Expenses'!$G$34
A7: Net Operating Cash Flow | B7: ='Income & Expenses'!$G$35
A8: Capital Improvements (see log) | B8: ='Deposits & Capital Improvements'!$F$20
A9: Security Deposits Currently Held | B9: ='Deposits & Capital Improvements'!$E$11
A10: Total Maintenance/Repair Spend (all logged) | B10: =SUM('Maintenance & Repairs'!$J$4:$J$18)
A13: Expenses by Category
A14: Repairs | B14: =SUMIFS('Income & Expenses'!$G$4:$G$31,'Income & Expenses'!$D$4:$D$31,"Expense",'Income & Expenses'!$E$4:$E$31,"Repairs")
A15: Maintenance | B15: =SUMIFS('Income & Expenses'!$G$4:$G$31,'Income & Expenses'!$D$4:$D$31,"Expense",'Income & Expenses'!$E$4:$E$31,"Maintenance")
A16: Utilities | B16: =SUMIFS('Income & Expenses'!$G$4:$G$31,'Income & Expenses'!$D$4:$D$31,"Expense",'Income & Expenses'!$E$4:$E$31,"Utilities")
A17: Insurance | B17: =SUMIFS('Income & Expenses'!$G$4:$G$31,'Income & Expenses'!$D$4:$D$31,"Expense",'Income & Expenses'!$E$4:$E$31,"Insurance")
A18: Property Tax | B18: =SUMIFS('Income & Expenses'!$G$4:$G$31,'Income & Expenses'!$D$4:$D$31,"Expense",'Income & Expenses'!$E$4:$E$31,"Property Tax")
A19: HOA | B19: =SUMIFS('Income & Expenses'!$G$4:$G$31,'Income & Expenses'!$D$4:$D$31,"Expense",'Income & Expenses'!$E$4:$E$31,"HOA")
A20: Management Fees | B20: =SUMIFS('Income & Expenses'!$G$4:$G$31,'Income & Expenses'!$D$4:$D$31,"Expense",'Income & Expenses'!$E$4:$E$31,"Management Fees")
A21: Cleaning | B21: =SUMIFS('Income & Expenses'!$G$4:$G$31,'Income & Expenses'!$D$4:$D$31,"Expense",'Income & Expenses'!$E$4:$E$31,"Cleaning")
A22: Supplies | B22: =SUMIFS('Income & Expenses'!$G$4:$G$31,'Income & Expenses'!$D$4:$D$31,"Expense",'Income & Expenses'!$E$4:$E$31,"Supplies")
A23: Advertising | B23: =SUMIFS('Income & Expenses'!$G$4:$G$31,'Income & Expenses'!$D$4:$D$31,"Expense",'Income & Expenses'!$E$4:$E$31,"Advertising")
A24: Legal/Professional | B24: =SUMIFS('Income & Expenses'!$G$4:$G$31,'Income & Expenses'!$D$4:$D$31,"Expense",'Income & Expenses'!$E$4:$E$31,"Legal/Professional")
A25: Mortgage Interest | B25: =SUMIFS('Income & Expenses'!$G$4:$G$31,'Income & Expenses'!$D$4:$D$31,"Expense",'Income & Expenses'!$E$4:$E$31,"Mortgage Interest")
A26: Travel/Mileage Log Reference | B26: =SUMIFS('Income & Expenses'!$G$4:$G$31,'Income & Expenses'!$D$4:$D$31,"Expense",'Income & Expenses'!$E$4:$E$31,"Travel/Mileage Log Reference")
A27: Other | B27: =SUMIFS('Income & Expenses'!$G$4:$G$31,'Income & Expenses'!$D$4:$D$31,"Expense",'Income & Expenses'!$E$4:$E$31,"Other")
A30: Property Comparison (Income / Expense / Net)
A31: Property | B31: Income | C31: Expenses | D31: Net
A32: P1 — Maple Ave Duplex | B32: =SUMIFS('Income & Expenses'!$G$4:$G$31,'Income & Expenses'!$B$4:$B$31,"P1",'Income & Expenses'!$D$4:$D$31,"Income") | C32: =SUMIFS('Income & Expenses'!$G$4:$G$31,'Income & Expenses'!$B$4:$B$31,"P1",'Income & Expenses'!$D$4:$D$31,"Expense") | D32: =B32-C32
A33: P2 — Oak Street Fourplex | B33: =SUMIFS('Income & Expenses'!$G$4:$G$31,'Income & Expenses'!$B$4:$B$31,"P2",'Income & Expenses'!$D$4:$D$31,"Income") | C33: =SUMIFS('Income & Expenses'!$G$4:$G$31,'Income & Expenses'!$B$4:$B$31,"P2",'Income & Expenses'!$D$4:$D$31,"Expense") | D33: =B33-C33
A34: P3 — Elm Court House | B34: =SUMIFS('Income & Expenses'!$G$4:$G$31,'Income & Expenses'!$B$4:$B$31,"P3",'Income & Expenses'!$D$4:$D$31,"Income") | C34: =SUMIFS('Income & Expenses'!$G$4:$G$31,'Income & Expenses'!$B$4:$B$31,"P3",'Income & Expenses'!$D$4:$D$31,"Expense") | D34: =B34-C34
A37: This is an organizational summary only, not a Schedule E filing, IRS submission, or CPA-reviewed document. Share it with your tax preparer as a starting point for their own work.
