Workbook

Sheet 00_START_HERE
A1: ESTATE SETTLEMENT COMMAND CENTER
A2: A connected workspace for organizing an estate after a death: tasks, assets, liabilities, transactions, documents, contacts, beneficiary records, a cash reconciliation check, and a closeout review — all in one place, updating automatically as you enter records.
A4: Estate / Reference Name | B4: Estate of Walter H. Doyle (sample)
A5: Date of Death | B5: 46192
A6: Jurisdiction (free text) | B6: Cook County, Illinois (example only -- enter your own)
A7: Executor / Administrator Name | B7: Nadia Doyle
A8: Starting Estate Cash | B8: 4200
A9: Actual Estate Cash Balance (as of today, from your bank statement) | B9: 9430
A11: ⚠ DO NOT double-count Starting Estate Cash as a transaction inflow on 05_ESTATE_TRANSACTIONS — it is the opening balance, entered once, here only.
A13: QUICK NAVIGATION — click a tab name to jump there
A14: → 01_COMMAND_CENTER
A15: → 02_ACTION_ROADMAP
A16: → 03_ASSET_REGISTER
A17: → 04_LIABILITY_REGISTER
A18: → 05_ESTATE_TRANSACTIONS
A19: → 06_EXPENSES_REIMBURSEMENTS
A20: → 07_DOCUMENT_CONTROL
A21: → 08_CONTACTS_COMMUNICATION
A22: → 09_BENEFICIARIES_DISTRIBUTIONS
A23: → 10_RECONCILIATION
... A34: WHAT THE COLORS MEAN
A35: YELLOW | B35: YOU TYPE HERE.
A36: WHITE | B36: AUTOMATIC — calculated for you. Don't type over these.
A38: WHAT THIS WORKBOOK IS NOT
A39: This is an organizational recordkeeping tool only. It does NOT determine whether probate is required, creditor priority, legal beneficiary entitlement, taxes owed, or legal distribution timing, and it does not tell you an estate is legally ready to close. "Organization Complete" on 11_CLOSEOUT_REVIEW means this workbook's own organizational flags are clear — nothing more. Always consult a qualified attorney or accountant for legal, tax, or probate questions.

Sheet 01_COMMAND_CENTER
A1: COMMAND CENTER
A3: Open Actions | B3: ='11_CLOSEOUT_REVIEW'!B4
A4: Completion Progress (tasks completed / total) | B4: =IFERROR(COUNTIF('02_ACTION_ROADMAP'!$G$4:$G$203,"Completed")/COUNTIF('02_ACTION_ROADMAP'!$A$4:$A$203,"<>"),0)
A5: Outstanding Documents | B5: ='11_CLOSEOUT_REVIEW'!B8
A6: Pending Reimbursements ($) | B6: ='11_CLOSEOUT_REVIEW'!B9
A7: Assets Identified (count) | B7: =COUNTIF('03_ASSET_REGISTER'!$A$4:$A$103,"<>")
A8: Known Liabilities (count) | B8: =COUNTIF('04_LIABILITY_REGISTER'!$A$4:$A$103,"<>")
A9: Expected Estate Cash ($) | B9: ='10_RECONCILIATION'!B7
A10: Reconciliation Difference ($) | B10: ='10_RECONCILIATION'!B9
A12: Organizational Closeout Status | B12: ='11_CLOSEOUT_REVIEW'!B14
A14: NEEDS ATTENTION NOW
A15: Overdue Tasks | B15: ='11_CLOSEOUT_REVIEW'!B5
A16: Unresolved Assets | B16: ='11_CLOSEOUT_REVIEW'!B6
A17: Unpaid / Disputed Liabilities | B17: ='11_CLOSEOUT_REVIEW'!B7
A18: Missing Transaction Evidence | B18: ='11_CLOSEOUT_REVIEW'!B12
A19: Reconciliation Status | B19: ='10_RECONCILIATION'!B13
A22: =IF('11_CLOSEOUT_REVIEW'!B14="SET UP ESTATE","→ SET UP ESTATE: fill in 00_START_HERE and add your first assets, liabilities, and transactions.","")
A25: CHART DATA (auto-calculated — do not edit)
A27: Category | B27: Amount
A28: Funeral Expenses | B28: =SUMIF('04_LIABILITY_REGISTER'!$C$4:$C$103,"Funeral Expenses",'04_LIABILITY_REGISTER'!$D$4:$D$103)
A29: Medical Bill | B29: =SUMIF('04_LIABILITY_REGISTER'!$C$4:$C$103,"Medical Bill",'04_LIABILITY_REGISTER'!$D$4:$D$103)
A30: Credit Card | B30: =SUMIF('04_LIABILITY_REGISTER'!$C$4:$C$103,"Credit Card",'04_LIABILITY_REGISTER'!$D$4:$D$103)
A31: Property Tax | B31: =SUMIF('04_LIABILITY_REGISTER'!$C$4:$C$103,"Property Tax",'04_LIABILITY_REGISTER'!$D$4:$D$103)
A32: Mortgage/Loan | B32: =SUMIF('04_LIABILITY_REGISTER'!$C$4:$C$103,"Mortgage/Loan",'04_LIABILITY_REGISTER'!$D$4:$D$103)
A33: Utility/Bank Fees | B33: =SUMIF('04_LIABILITY_REGISTER'!$C$4:$C$103,"Utility/Bank Fees",'04_LIABILITY_REGISTER'!$D$4:$D$103)
A34: Other | B34: =SUMIF('04_LIABILITY_REGISTER'!$C$4:$C$103,"Other",'04_LIABILITY_REGISTER'!$D$4:$D$103)
A37: Status | B37: Count
A38: Collected | B38: =COUNTIF('03_ASSET_REGISTER'!$J$4:$J$103,"Collected")
A39: Sold | B39: =COUNTIF('03_ASSET_REGISTER'!$J$4:$J$103,"Sold")
A40: Distributed In-Kind | B40: =COUNTIF('03_ASSET_REGISTER'!$J$4:$J$103,"Distributed In-Kind")
A41: Not Yet Disposed | B41: =COUNTIF('03_ASSET_REGISTER'!$J$4:$J$103,"Not Yet Disposed")
A42: Unresolved | B42: =COUNTIF('03_ASSET_REGISTER'!$J$4:$J$103,"Unresolved")

Sheet 02_ACTION_ROADMAP
A1: ACTION ROADMAP
A2: One row per task. Add your own tasks below the sample rows — the workbook keeps working.
A3: Task ID | B3: Phase | C3: Task | D3: Category | E3: Owner | F3: Target Date | G3: Status | H3: Priority | I3: Blocked By | J3: Follow-up Date | K3: Evidence / Location | L3: Warning (auto)
A4: T1 | B4: First 30 Days | C4: Notify Social Security Administration | D4: Administrative | E4: Nadia Doyle | F4: 46207 | G4: Completed | H4: High | K4: Confirmation letter, home filing box | L4: =IF($A4="","",IF($G4="Completed","",IF(AND($F4<>"",$F4<TODAY(),$G4<>"Completed"),"⚠ overdue",IF(AND($F4<>"",$F4>=TODAY(),$F4-TODAY()<=7),"⚠ due soon",""))))
A5: T2 | B5: First 30 Days | C5: Obtain certified copies of death certificate | D5: Administrative | E5: Nadia Doyle | F5: 46202 | G5: Completed | H5: High | K5: 10 copies, home safe | L5: =IF($A5="","",IF($G5="Completed","",IF(AND($F5<>"",$F5<TODAY(),$G5<>"Completed"),"⚠ overdue",IF(AND($F5<>"",$F5>=TODAY(),$F5-TODAY()<=7),"⚠ due soon",""))))
A6: T3 | B6: First 30 Days | C6: Open estate bank account | D6: Financial | E6: Nadia Doyle | F6: 46217 | G6: Completed | H6: High | K6: First National Estate Acct ...3391 | L6: =IF($A6="","",IF($G6="Completed","",IF(AND($F6<>"",$F6<TODAY(),$G6<>"Completed"),"⚠ overdue",IF(AND($F6<>"",$F6>=TODAY(),$F6-TODAY()<=7),"⚠ due soon",""))))
A7: T4 | B7: First 30 Days | C7: File will for probate | D7: Legal | E7: Nadia Doyle | F7: 46227 | G7: Completed | H7: High | K7: Filed with county probate clerk | L7: =IF($A7="","",IF($G7="Completed","",IF(AND($F7<>"",$F7<TODAY(),$G7<>"Completed"),"⚠ overdue",IF(AND($F7<>"",$F7>=TODAY(),$F7-TODAY()<=7),"⚠ due soon",""))))
A8: T5 | B8: 30-60 Days | C8: Locate and inventory safe deposit box | D8: Assets | E8: Nadia Doyle | F8: 46247 | G8: Completed | H8: Medium | K8: First National Bank branch | L8: =IF($A8="","",IF($G8="Completed","",IF(AND($F8<>"",$F8<TODAY(),$G8<>"Completed"),"⚠ overdue",IF(AND($F8<>"",$F8>=TODAY(),$F8-TODAY()<=7),"⚠ due soon",""))))
A9: T6 | B9: 30-60 Days | C9: Get home appraised | D9: Assets | E9: Nadia Doyle | F9: 46292 | G9: Open | H9: Medium | L9: =IF($A9="","",IF($G9="Completed","",IF(AND($F9<>"",$F9<TODAY(),$G9<>"Completed"),"⚠ overdue",IF(AND($F9<>"",$F9>=TODAY(),$F9-TODAY()<=7),"⚠ due soon",""))))
A10: T7 | B10: 30-60 Days | C10: Cancel deceased's subscriptions/utilities not needed | D10: Administrative | E10: Nadia Doyle | F10: 46277 | G10: Open | H10: Low | L10: =IF($A10="","",IF($G10="Completed","",IF(AND($F10<>"",$F10<TODAY(),$G10<>"Completed"),"⚠ overdue",IF(AND($F10<>"",$F10>=TODAY(),$F10-TODAY()<=7),"⚠ due soon",""))))
A11: T8 | B11: First 30 Days | C11: Notify life insurance carrier | D11: Financial | E11: Nadia Doyle | F11: 46212 | G11: Completed | H11: High | K11: Claim confirmation email | L11: =IF($A11="","",IF($G11="Completed","",IF(AND($F11<>"",$F11<TODAY(),$G11<>"Completed"),"⚠ overdue",IF(AND($F11<>"",$F11>=TODAY(),$F11-TODAY()<=7),"⚠ due soon",""))))
A12: T9 | B12: 30-60 Days | C12: Respond to creditor claim -- Meridian Card Services | D12: Liabilities | E12: Nadia Doyle | F12: 46299 | G12: Open | H12: Medium | I12: Awaiting verified amount | L12: =IF($A12="","",IF($G12="Completed","",IF(AND($F12<>"",$F12<TODAY(),$G12<>"Completed"),"⚠ overdue",IF(AND($F12<>"",$F12>=TODAY(),$F12-TODAY()<=7),"⚠ due soon",""))))
A13: T10 | B13: 60-90 Days | C13: Prepare beneficiary distribution schedule (draft) | D13: Distributions | E13: Nadia Doyle | F13: 46317 | G13: Open | H13: Medium | I13: Home appraisal | J13: 46307 | L13: =IF($A13="","",IF($G13="Completed","",IF(AND($F13<>"",$F13<TODAY(),$G13<>"Completed"),"⚠ overdue",IF(AND($F13<>"",$F13>=TODAY(),$F13-TODAY()<=7),"⚠ due soon",""))))
A14: T11 | B14: 30-60 Days | C14: Follow up on outstanding utility refund | D14: Financial | E14: Nadia Doyle | F14: 46284 | G14: Waiting | H14: Low | J14: 46294 | L14: =IF($A14="","",IF($G14="Completed","",IF(AND($F14<>"",$F14<TODAY(),$G14<>"Completed"),"⚠ overdue",IF(AND($F14<>"",$F14>=TODAY(),$F14-TODAY()<=7),"⚠ due soon",""))))
A15: T12 | B15: 60-90 Days | C15: Confirm final property tax bill | D15: Liabilities | E15: Nadia Doyle | F15: 46312 | G15: Open | H15: Medium | L15: =IF($A15="","",IF($G15="Completed","",IF(AND($F15<>"",$F15<TODAY(),$G15<>"Completed"),"⚠ overdue",IF(AND($F15<>"",$F15>=TODAY(),$F15-TODAY()<=7),"⚠ due soon",""))))
L16: =IF($A16="","",IF($G16="Completed","",IF(AND($F16<>"",$F16<TODAY(),$G16<>"Completed"),"⚠ overdue",IF(AND($F16<>"",$F16>=TODAY(),$F16-TODAY()<=7),"⚠ due soon",""))))
L17: =IF($A17="","",IF($G17="Completed","",IF(AND($F17<>"",$F17<TODAY(),$G17<>"Completed"),"⚠ overdue",IF(AND($F17<>"",$F17>=TODAY(),$F17-TODAY()<=7),"⚠ due soon",""))))
L18: =IF($A18="","",IF($G18="Completed","",IF(AND($F18<>"",$F18<TODAY(),$G18<>"Completed"),"⚠ overdue",IF(AND($F18<>"",$F18>=TODAY(),$F18-TODAY()<=7),"⚠ due soon",""))))
L19: =IF($A19="","",IF($G19="Completed","",IF(AND($F19<>"",$F19<TODAY(),$G19<>"Completed"),"⚠ overdue",IF(AND($F19<>"",$F19>=TODAY(),$F19-TODAY()<=7),"⚠ due soon",""))))
L20: =IF($A20="","",IF($G20="Completed","",IF(AND($F20<>"",$F20<TODAY(),$G20<>"Completed"),"⚠ overdue",IF(AND($F20<>"",$F20>=TODAY(),$F20-TODAY()<=7),"⚠ due soon",""))))
L21: =IF($A21="","",IF($G21="Completed","",IF(AND($F21<>"",$F21<TODAY(),$G21<>"Completed"),"⚠ overdue",IF(AND($F21<>"",$F21>=TODAY(),$F21-TODAY()<=7),"⚠ due soon",""))))
L22: =IF($A22="","",IF($G22="Completed","",IF(AND($F22<>"",$F22<TODAY(),$G22<>"Completed"),"⚠ overdue",IF(AND($F22<>"",$F22>=TODAY(),$F22-TODAY()<=7),"⚠ due soon",""))))
L23: =IF($A23="","",IF($G23="Completed","",IF(AND($F23<>"",$F23<TODAY(),$G23<>"Completed"),"⚠ overdue",IF(AND($F23<>"",$F23>=TODAY(),$F23-TODAY()<=7),"⚠ due soon",""))))
L24: =IF($A24="","",IF($G24="Completed","",IF(AND($F24<>"",$F24<TODAY(),$G24<>"Completed"),"⚠ overdue",IF(AND($F24<>"",$F24>=TODAY(),$F24-TODAY()<=7),"⚠ due soon",""))))
L25: =IF($A25="","",IF($G25="Completed","",IF(AND($F25<>"",$F25<TODAY(),$G25<>"Completed"),"⚠ overdue",IF(AND($F25<>"",$F25>=TODAY(),$F25-TODAY()<=7),"⚠ due soon",""))))
L26: =IF($A26="","",IF($G26="Completed","",IF(AND($F26<>"",$F26<TODAY(),$G26<>"Completed"),"⚠ overdue",IF(AND($F26<>"",$F26>=TODAY(),$F26-TODAY()<=7),"⚠ due soon",""))))
L27: =IF($A27="","",IF($G27="Completed","",IF(AND($F27<>"",$F27<TODAY(),$G27<>"Completed"),"⚠ overdue",IF(AND($F27<>"",$F27>=TODAY(),$F27-TODAY()<=7),"⚠ due soon",""))))
... L203: =IF($A203="","",IF($G203="Completed","",IF(AND($F203<>"",$F203<TODAY(),$G203<>"Completed"),"⚠ overdue",IF(AND($F203<>"",$F203>=TODAY(),$F203-TODAY()<=7),"⚠ due soon",""))))

Sheet 03_ASSET_REGISTER
A1: ASSET REGISTER
A2: Not every asset is automatically "collected" — disposition differs by asset type. The Warning column flags what still needs attention.
A3: Asset ID | B3: Asset Type | C3: Institution / Description | D3: Ownership/Title Notes | E3: Estimated Value | F3: Valuation Date | G3: Reference Suffix | H3: Located? | I3: Documentation Status | J3: Disposition/Collection Status | K3: Actual Amount Received | L3: Date Received | M3: Warning (auto)
A4: A1 | B4: Checking Account | C4: First National Bank | D4: Individual, sole owner | E4: 6250 | F4: 46199 | G4: ...3391 | H4: Yes | I4: Complete | J4: Collected | K4: 6250 | L4: 46217 | M4: =IF($A4="","",IF($H4="No","⚠ not located",IF($J4="Unresolved","⚠ unresolved disposition",IF($I4="Missing","⚠ documentation missing",""))))
A5: A2 | B5: Home -- 214 Larkspur Ave | C5: Primary residence | D5: Sole owner, no mortgage | E5: 385000 | F5: 46237 | H5: Yes | I5: Pending Appraisal | J5: Not Yet Disposed | K5: 0 | M5: =IF($A5="","",IF($H5="No","⚠ not located",IF($J5="Unresolved","⚠ unresolved disposition",IF($I5="Missing","⚠ documentation missing",""))))
A6: A3 | B6: Life Insurance Policy | C6: Meridian Life | D6: Estate named as backup beneficiary | E6: 15000 | F6: 46212 | G6: Policy ...8820 | H6: Yes | I6: Complete | J6: Collected | K6: 15000 | L6: 46227 | M6: =IF($A6="","",IF($H6="No","⚠ not located",IF($J6="Unresolved","⚠ unresolved disposition",IF($I6="Missing","⚠ documentation missing",""))))
A7: A4 | B7: Vehicle -- 2019 Sedan | C7: Personal property | D7: Sole owner | E7: 11500 | F7: 46207 | G7: VIN ...4471 | H7: Yes | I7: Complete | J7: Not Yet Disposed | K7: 0 | M7: =IF($A7="","",IF($H7="No","⚠ not located",IF($J7="Unresolved","⚠ unresolved disposition",IF($I7="Missing","⚠ documentation missing",""))))
A8: A5 | B8: Safe Deposit Box Contents | C8: First National Bank | D8: Contents not yet fully valued | E8: 0 | H8: No | I8: Missing | J8: Unresolved | K8: 0 | M8: =IF($A8="","",IF($H8="No","⚠ not located",IF($J8="Unresolved","⚠ unresolved disposition",IF($I8="Missing","⚠ documentation missing",""))))
A9: A6 | B9: Brokerage Account | C9: Vantage Investments | D9: Individual, sole owner | E9: 22400 | F9: 46205 | G9: ...5510 | H9: Yes | I9: Complete | J9: Collected | K9: 22400 | L9: 46232 | M9: =IF($A9="","",IF($H9="No","⚠ not located",IF($J9="Unresolved","⚠ unresolved disposition",IF($I9="Missing","⚠ documentation missing",""))))
M10: =IF($A10="","",IF($H10="No","⚠ not located",IF($J10="Unresolved","⚠ unresolved disposition",IF($I10="Missing","⚠ documentation missing",""))))
M11: =IF($A11="","",IF($H11="No","⚠ not located",IF($J11="Unresolved","⚠ unresolved disposition",IF($I11="Missing","⚠ documentation missing",""))))
M12: =IF($A12="","",IF($H12="No","⚠ not located",IF($J12="Unresolved","⚠ unresolved disposition",IF($I12="Missing","⚠ documentation missing",""))))
M13: =IF($A13="","",IF($H13="No","⚠ not located",IF($J13="Unresolved","⚠ unresolved disposition",IF($I13="Missing","⚠ documentation missing",""))))
M14: =IF($A14="","",IF($H14="No","⚠ not located",IF($J14="Unresolved","⚠ unresolved disposition",IF($I14="Missing","⚠ documentation missing",""))))
M15: =IF($A15="","",IF($H15="No","⚠ not located",IF($J15="Unresolved","⚠ unresolved disposition",IF($I15="Missing","⚠ documentation missing",""))))
M16: =IF($A16="","",IF($H16="No","⚠ not located",IF($J16="Unresolved","⚠ unresolved disposition",IF($I16="Missing","⚠ documentation missing",""))))
M17: =IF($A17="","",IF($H17="No","⚠ not located",IF($J17="Unresolved","⚠ unresolved disposition",IF($I17="Missing","⚠ documentation missing",""))))
M18: =IF($A18="","",IF($H18="No","⚠ not located",IF($J18="Unresolved","⚠ unresolved disposition",IF($I18="Missing","⚠ documentation missing",""))))
M19: =IF($A19="","",IF($H19="No","⚠ not located",IF($J19="Unresolved","⚠ unresolved disposition",IF($I19="Missing","⚠ documentation missing",""))))
M20: =IF($A20="","",IF($H20="No","⚠ not located",IF($J20="Unresolved","⚠ unresolved disposition",IF($I20="Missing","⚠ documentation missing",""))))
M21: =IF($A21="","",IF($H21="No","⚠ not located",IF($J21="Unresolved","⚠ unresolved disposition",IF($I21="Missing","⚠ documentation missing",""))))
... M103: =IF($A103="","",IF($H103="No","⚠ not located",IF($J103="Unresolved","⚠ unresolved disposition",IF($I103="Missing","⚠ documentation missing",""))))

Sheet 04_LIABILITY_REGISTER
A1: LIABILITY REGISTER
A2: This workbook does not determine creditor priority or whether a debt is legally owed — it tracks what's claimed, verified, and paid, for your own organization.
A3: Liability ID | B3: Creditor | C3: Category | D3: Amount Claimed | E3: Amount Verified | F3: Due Date | G3: Disputed? | H3: Status | I3: Amount Paid | J3: Payment Date | K3: Warning (auto)
A4: L1 | B4: First National Bank | C4: Final Utility/Bank Fees | D4: 180 | E4: 180 | F4: 46257 | G4: No | H4: Paid | I4: 180 | J4: 46262 | K4: =IF($A4="","",IF($H4="Disputed","⚠ disputed item",IF(AND($H4="Verified, Unpaid",IF(ISNUMBER($E4),$E4,0)>IF(ISNUMBER($I4),$I4,0)),"⚠ unpaid verified balance","")))
A5: L2 | B5: Meridian Card Services | C5: Credit Card | D5: 3400 | E5: 0 | F5: 46302 | G5: Yes | H5: Disputed | I5: 0 | K5: =IF($A5="","",IF($H5="Disputed","⚠ disputed item",IF(AND($H5="Verified, Unpaid",IF(ISNUMBER($E5),$E5,0)>IF(ISNUMBER($I5),$I5,0)),"⚠ unpaid verified balance","")))
A6: L3 | B6: Lakeside Funeral Home | C6: Funeral Expenses | D6: 8900 | E6: 8900 | F6: 46217 | G6: No | H6: Verified, Unpaid | I6: 0 | K6: =IF($A6="","",IF($H6="Disputed","⚠ disputed item",IF(AND($H6="Verified, Unpaid",IF(ISNUMBER($E6),$E6,0)>IF(ISNUMBER($I6),$I6,0)),"⚠ unpaid verified balance","")))
A7: L4 | B7: County Tax Assessor | C7: Property Tax | D7: 2100 | E7: 2100 | F7: 46307 | G7: No | H7: Verified, Unpaid | I7: 0 | K7: =IF($A7="","",IF($H7="Disputed","⚠ disputed item",IF(AND($H7="Verified, Unpaid",IF(ISNUMBER($E7),$E7,0)>IF(ISNUMBER($I7),$I7,0)),"⚠ unpaid verified balance","")))
A8: L5 | B8: Dr. Ellen Farrow, DDS | C8: Medical Bill | D8: 340 | E8: 340 | F8: 46282 | G8: No | H8: Verified, Unpaid | I8: 0 | K8: =IF($A8="","",IF($H8="Disputed","⚠ disputed item",IF(AND($H8="Verified, Unpaid",IF(ISNUMBER($E8),$E8,0)>IF(ISNUMBER($I8),$I8,0)),"⚠ unpaid verified balance","")))
K9: =IF($A9="","",IF($H9="Disputed","⚠ disputed item",IF(AND($H9="Verified, Unpaid",IF(ISNUMBER($E9),$E9,0)>IF(ISNUMBER($I9),$I9,0)),"⚠ unpaid verified balance","")))
K10: =IF($A10="","",IF($H10="Disputed","⚠ disputed item",IF(AND($H10="Verified, Unpaid",IF(ISNUMBER($E10),$E10,0)>IF(ISNUMBER($I10),$I10,0)),"⚠ unpaid verified balance","")))
K11: =IF($A11="","",IF($H11="Disputed","⚠ disputed item",IF(AND($H11="Verified, Unpaid",IF(ISNUMBER($E11),$E11,0)>IF(ISNUMBER($I11),$I11,0)),"⚠ unpaid verified balance","")))
K12: =IF($A12="","",IF($H12="Disputed","⚠ disputed item",IF(AND($H12="Verified, Unpaid",IF(ISNUMBER($E12),$E12,0)>IF(ISNUMBER($I12),$I12,0)),"⚠ unpaid verified balance","")))
K13: =IF($A13="","",IF($H13="Disputed","⚠ disputed item",IF(AND($H13="Verified, Unpaid",IF(ISNUMBER($E13),$E13,0)>IF(ISNUMBER($I13),$I13,0)),"⚠ unpaid verified balance","")))
K14: =IF($A14="","",IF($H14="Disputed","⚠ disputed item",IF(AND($H14="Verified, Unpaid",IF(ISNUMBER($E14),$E14,0)>IF(ISNUMBER($I14),$I14,0)),"⚠ unpaid verified balance","")))
K15: =IF($A15="","",IF($H15="Disputed","⚠ disputed item",IF(AND($H15="Verified, Unpaid",IF(ISNUMBER($E15),$E15,0)>IF(ISNUMBER($I15),$I15,0)),"⚠ unpaid verified balance","")))
K16: =IF($A16="","",IF($H16="Disputed","⚠ disputed item",IF(AND($H16="Verified, Unpaid",IF(ISNUMBER($E16),$E16,0)>IF(ISNUMBER($I16),$I16,0)),"⚠ unpaid verified balance","")))
K17: =IF($A17="","",IF($H17="Disputed","⚠ disputed item",IF(AND($H17="Verified, Unpaid",IF(ISNUMBER($E17),$E17,0)>IF(ISNUMBER($I17),$I17,0)),"⚠ unpaid verified balance","")))
K18: =IF($A18="","",IF($H18="Disputed","⚠ disputed item",IF(AND($H18="Verified, Unpaid",IF(ISNUMBER($E18),$E18,0)>IF(ISNUMBER($I18),$I18,0)),"⚠ unpaid verified balance","")))
K19: =IF($A19="","",IF($H19="Disputed","⚠ disputed item",IF(AND($H19="Verified, Unpaid",IF(ISNUMBER($E19),$E19,0)>IF(ISNUMBER($I19),$I19,0)),"⚠ unpaid verified balance","")))
K20: =IF($A20="","",IF($H20="Disputed","⚠ disputed item",IF(AND($H20="Verified, Unpaid",IF(ISNUMBER($E20),$E20,0)>IF(ISNUMBER($I20),$I20,0)),"⚠ unpaid verified balance","")))
... K103: =IF($A103="","",IF($H103="Disputed","⚠ disputed item",IF(AND($H103="Verified, Unpaid",IF(ISNUMBER($E103),$E103,0)>IF(ISNUMBER($I103),$I103,0)),"⚠ unpaid verified balance","")))

Sheet 05_ESTATE_TRANSACTIONS
A1: ESTATE TRANSACTIONS
A2: The source of truth for cash movement. Do NOT enter Starting Estate Cash here — that lives on 00_START_HERE only.
A3: Transaction ID | B3: Date | C3: Transaction Type | D3: Category | E3: Payee/Payer | F3: Description | G3: Inflow | H3: Outflow | I3: Linked ID | J3: Source Account | K3: Evidence Status | L3: Warning (auto)
A4: T1 | B4: 46217 | C4: Deposit | D4: Asset Collection | E4: First National Bank | F4: Checking account transferred to estate account | G4: 6250 | H4: 0 | I4: A1 | J4: Estate Acct ...3391 | K4: Provided | L4: =IF($A4="","",IF(AND(ISNUMBER($G4),ISNUMBER($H4),$G4>0,$H4>0),"⚠ both inflow and outflow entered",IF($K4="Missing","⚠ missing evidence","")))
A5: T2 | B5: 46219 | C5: Payment | D5: Liability | E5: Lakeside Funeral Home | F5: Funeral expenses paid | G5: 0 | H5: 8900 | I5: L3 | J5: Estate Acct ...3391 | K5: Provided | L5: =IF($A5="","",IF(AND(ISNUMBER($G5),ISNUMBER($H5),$G5>0,$H5>0),"⚠ both inflow and outflow entered",IF($K5="Missing","⚠ missing evidence","")))
A6: T3 | B6: 46227 | C6: Deposit | D6: Asset Collection | E6: Meridian Life | F6: Life insurance proceeds | G6: 0 | H6: 0 | I6: A3 | J6: Estate Acct ...3391 | K6: Missing | L6: =IF($A6="","",IF(AND(ISNUMBER($G6),ISNUMBER($H6),$G6>0,$H6>0),"⚠ both inflow and outflow entered",IF($K6="Missing","⚠ missing evidence","")))
A7: T3b | B7: 46227 | C7: Deposit | D7: Asset Collection | E7: Meridian Life | F7: Life insurance proceeds | G7: 15000 | H7: 0 | I7: A3 | J7: Estate Acct ...3391 | K7: Provided | L7: =IF($A7="","",IF(AND(ISNUMBER($G7),ISNUMBER($H7),$G7>0,$H7>0),"⚠ both inflow and outflow entered",IF($K7="Missing","⚠ missing evidence","")))
A8: T4 | B8: 46232 | C8: Deposit | D8: Asset Collection | E8: Vantage Investments | F8: Brokerage account liquidated | G8: 22400 | H8: 0 | I8: A6 | J8: Estate Acct ...3391 | K8: Provided | L8: =IF($A8="","",IF(AND(ISNUMBER($G8),ISNUMBER($H8),$G8>0,$H8>0),"⚠ both inflow and outflow entered",IF($K8="Missing","⚠ missing evidence","")))
A9: T5 | B9: 46262 | C9: Payment | D9: Liability | E9: First National Bank | F9: Final bank fees paid | G9: 0 | H9: 180 | I9: L1 | J9: Estate Acct ...3391 | K9: Provided | L9: =IF($A9="","",IF(AND(ISNUMBER($G9),ISNUMBER($H9),$G9>0,$H9>0),"⚠ both inflow and outflow entered",IF($K9="Missing","⚠ missing evidence","")))
A10: T6 | B10: 46269 | C10: Payment | D10: Expense | E10: Doyle Estate Law Group | F10: Attorney retainer | G10: 0 | H10: 1500 | J10: Estate Acct ...3391 | K10: Provided | L10: =IF($A10="","",IF(AND(ISNUMBER($G10),ISNUMBER($H10),$G10>0,$H10>0),"⚠ both inflow and outflow entered",IF($K10="Missing","⚠ missing evidence","")))
A11: T7 | B11: 46273 | C11: Deposit | D11: Refund | E11: City Utilities Co | F11: Utility deposit refund | G11: 220 | H11: 0 | J11: Estate Acct ...3391 | K11: Not Applicable | L11: =IF($A11="","",IF(AND(ISNUMBER($G11),ISNUMBER($H11),$G11>0,$H11>0),"⚠ both inflow and outflow entered",IF($K11="Missing","⚠ missing evidence","")))
L12: =IF($A12="","",IF(AND(ISNUMBER($G12),ISNUMBER($H12),$G12>0,$H12>0),"⚠ both inflow and outflow entered",IF($K12="Missing","⚠ missing evidence","")))
L13: =IF($A13="","",IF(AND(ISNUMBER($G13),ISNUMBER($H13),$G13>0,$H13>0),"⚠ both inflow and outflow entered",IF($K13="Missing","⚠ missing evidence","")))
L14: =IF($A14="","",IF(AND(ISNUMBER($G14),ISNUMBER($H14),$G14>0,$H14>0),"⚠ both inflow and outflow entered",IF($K14="Missing","⚠ missing evidence","")))
L15: =IF($A15="","",IF(AND(ISNUMBER($G15),ISNUMBER($H15),$G15>0,$H15>0),"⚠ both inflow and outflow entered",IF($K15="Missing","⚠ missing evidence","")))
L16: =IF($A16="","",IF(AND(ISNUMBER($G16),ISNUMBER($H16),$G16>0,$H16>0),"⚠ both inflow and outflow entered",IF($K16="Missing","⚠ missing evidence","")))
L17: =IF($A17="","",IF(AND(ISNUMBER($G17),ISNUMBER($H17),$G17>0,$H17>0),"⚠ both inflow and outflow entered",IF($K17="Missing","⚠ missing evidence","")))
L18: =IF($A18="","",IF(AND(ISNUMBER($G18),ISNUMBER($H18),$G18>0,$H18>0),"⚠ both inflow and outflow entered",IF($K18="Missing","⚠ missing evidence","")))
L19: =IF($A19="","",IF(AND(ISNUMBER($G19),ISNUMBER($H19),$G19>0,$H19>0),"⚠ both inflow and outflow entered",IF($K19="Missing","⚠ missing evidence","")))
L20: =IF($A20="","",IF(AND(ISNUMBER($G20),ISNUMBER($H20),$G20>0,$H20>0),"⚠ both inflow and outflow entered",IF($K20="Missing","⚠ missing evidence","")))
L21: =IF($A21="","",IF(AND(ISNUMBER($G21),ISNUMBER($H21),$G21>0,$H21>0),"⚠ both inflow and outflow entered",IF($K21="Missing","⚠ missing evidence","")))
L22: =IF($A22="","",IF(AND(ISNUMBER($G22),ISNUMBER($H22),$G22>0,$H22>0),"⚠ both inflow and outflow entered",IF($K22="Missing","⚠ missing evidence","")))
L23: =IF($A23="","",IF(AND(ISNUMBER($G23),ISNUMBER($H23),$G23>0,$H23>0),"⚠ both inflow and outflow entered",IF($K23="Missing","⚠ missing evidence","")))
... L503: =IF($A503="","",IF(AND(ISNUMBER($G503),ISNUMBER($H503),$G503>0,$H503>0),"⚠ both inflow and outflow entered",IF($K503="Missing","⚠ missing evidence","")))

Sheet 06_EXPENSES_REIMBURSEMENTS
A1: EXPENSES & REIMBURSEMENTS
A2: Distinguishes an estate-paid expense from an executor/family advance that still needs reimbursing.
A3: Description | B3: Date | C3: Category | D3: Notes | E3: Payer | F3: Type | G3: Amount | H3: Reimbursement Requested? | I3: Reimbursement Paid? | J3: Amount Reimbursed | K3: Evidence Status | L3: Outstanding (auto)
A4: Attorney retainer | B4: 46269 | C4: Professional Fees | D4: Estate attorney initial retainer | E4: Estate | F4: Estate-Paid | G4: 1500 | H4: N/A | I4: N/A | J4: 0 | K4: Provided | L4: =IF($A4="",0,IF($H4="Yes",IF(ISNUMBER($G4),$G4,0)-IF(ISNUMBER($J4),$J4,0),0))
A5: Locksmith -- change home locks | B5: 46205 | C5: Property Maintenance | D5: Rekey residence after death | E5: Nadia Doyle | F5: Executor Advance | G5: 145 | H5: Yes | I5: Yes | J5: 145 | K5: Provided | L5: =IF($A5="",0,IF($H5="Yes",IF(ISNUMBER($G5),$G5,0)-IF(ISNUMBER($J5),$J5,0),0))
A6: Travel to probate filing | B6: 46227 | C6: Executor Travel | D6: Mileage to county courthouse | E6: Nadia Doyle | F6: Executor Advance | G6: 38.5 | H6: Yes | I6: No | J6: 0 | K6: Provided | L6: =IF($A6="",0,IF($H6="Yes",IF(ISNUMBER($G6),$G6,0)-IF(ISNUMBER($J6),$J6,0),0))
A7: Storage unit -- household goods | B7: 46247 | C7: Property Maintenance | D7: Month 1 storage | E7: Nadia Doyle | F7: Executor Advance | G7: 95 | H7: Yes | I7: Partial | J7: 50 | K7: Provided | L7: =IF($A7="",0,IF($H7="Yes",IF(ISNUMBER($G7),$G7,0)-IF(ISNUMBER($J7),$J7,0),0))
A8: Certified mail -- creditor notices | B8: 46257 | C8: Administrative | D8: Certified mail to known creditors | E8: Nadia Doyle | F8: Executor Advance | G8: 22.4 | H8: No | I8: N/A | J8: 0 | K8: Not Applicable | L8: =IF($A8="",0,IF($H8="Yes",IF(ISNUMBER($G8),$G8,0)-IF(ISNUMBER($J8),$J8,0),0))
L9: =IF($A9="",0,IF($H9="Yes",IF(ISNUMBER($G9),$G9,0)-IF(ISNUMBER($J9),$J9,0),0))
L10: =IF($A10="",0,IF($H10="Yes",IF(ISNUMBER($G10),$G10,0)-IF(ISNUMBER($J10),$J10,0),0))
L11: =IF($A11="",0,IF($H11="Yes",IF(ISNUMBER($G11),$G11,0)-IF(ISNUMBER($J11),$J11,0),0))
L12: =IF($A12="",0,IF($H12="Yes",IF(ISNUMBER($G12),$G12,0)-IF(ISNUMBER($J12),$J12,0),0))
L13: =IF($A13="",0,IF($H13="Yes",IF(ISNUMBER($G13),$G13,0)-IF(ISNUMBER($J13),$J13,0),0))
L14: =IF($A14="",0,IF($H14="Yes",IF(ISNUMBER($G14),$G14,0)-IF(ISNUMBER($J14),$J14,0),0))
L15: =IF($A15="",0,IF($H15="Yes",IF(ISNUMBER($G15),$G15,0)-IF(ISNUMBER($J15),$J15,0),0))
L16: =IF($A16="",0,IF($H16="Yes",IF(ISNUMBER($G16),$G16,0)-IF(ISNUMBER($J16),$J16,0),0))
L17: =IF($A17="",0,IF($H17="Yes",IF(ISNUMBER($G17),$G17,0)-IF(ISNUMBER($J17),$J17,0),0))
L18: =IF($A18="",0,IF($H18="Yes",IF(ISNUMBER($G18),$G18,0)-IF(ISNUMBER($J18),$J18,0),0))
L19: =IF($A19="",0,IF($H19="Yes",IF(ISNUMBER($G19),$G19,0)-IF(ISNUMBER($J19),$J19,0),0))
L20: =IF($A20="",0,IF($H20="Yes",IF(ISNUMBER($G20),$G20,0)-IF(ISNUMBER($J20),$J20,0),0))
... L303: =IF($A303="",0,IF($H303="Yes",IF(ISNUMBER($G303),$G303,0)-IF(ISNUMBER($J303),$J303,0),0))

Sheet 07_DOCUMENT_CONTROL
A1: DOCUMENT CONTROL
A2: Not a jurisdiction-specific legal completeness checklist — a tracker for the documents you decide you need.
A3: Document / Item | B3: Category | C3: Required? | D3: Requested Date | E3: Received Date | F3: Institution | G3: Related Task ID | H3: Status | I3: Warning (auto)
A4: Certified Death Certificate | B4: Legal | C4: Yes | D4: 46197 | E4: 46202 | F4: County Vital Records | H4: Received | I4: =IF($A4="","",IF($H4="Not Applicable","",IF(AND($H4="Requested",$D4<>"",TODAY()-$D4>14),"⚠ requested >14 days ago",IF(AND($C4="Yes",$H4<>"Received"),"⚠ outstanding item",""))))
A5: Original Will | B5: Legal | C5: Yes | D5: 46197 | E5: 46199 | F5: Cook County Probate Court | H5: Received | I5: =IF($A5="","",IF($H5="Not Applicable","",IF(AND($H5="Requested",$D5<>"",TODAY()-$D5>14),"⚠ requested >14 days ago",IF(AND($C5="Yes",$H5<>"Received"),"⚠ outstanding item",""))))
A6: Life Insurance Policy Document | B6: Financial | C6: Yes | D6: 46209 | E6: 46212 | F6: Meridian Life | H6: Received | I6: =IF($A6="","",IF($H6="Not Applicable","",IF(AND($H6="Requested",$D6<>"",TODAY()-$D6>14),"⚠ requested >14 days ago",IF(AND($C6="Yes",$H6<>"Received"),"⚠ outstanding item",""))))
A7: Home Appraisal Report | B7: Financial | C7: Yes | D7: 46277 | F7: Riverside Appraisals | H7: Requested | I7: =IF($A7="","",IF($H7="Not Applicable","",IF(AND($H7="Requested",$D7<>"",TODAY()-$D7>14),"⚠ requested >14 days ago",IF(AND($C7="Yes",$H7<>"Received"),"⚠ outstanding item",""))))
A8: Brokerage Account Statement (final) | B8: Financial | C8: Yes | D8: 46227 | E8: 46229 | F8: Vantage Investments | H8: Received | I8: =IF($A8="","",IF($H8="Not Applicable","",IF(AND($H8="Requested",$D8<>"",TODAY()-$D8>14),"⚠ requested >14 days ago",IF(AND($C8="Yes",$H8<>"Received"),"⚠ outstanding item",""))))
A9: Vehicle Title | B9: Legal | C9: No | F9: N/A | H9: Not Applicable | I9: =IF($A9="","",IF($H9="Not Applicable","",IF(AND($H9="Requested",$D9<>"",TODAY()-$D9>14),"⚠ requested >14 days ago",IF(AND($C9="Yes",$H9<>"Received"),"⚠ outstanding item",""))))
I10: =IF($A10="","",IF($H10="Not Applicable","",IF(AND($H10="Requested",$D10<>"",TODAY()-$D10>14),"⚠ requested >14 days ago",IF(AND($C10="Yes",$H10<>"Received"),"⚠ outstanding item",""))))
I11: =IF($A11="","",IF($H11="Not Applicable","",IF(AND($H11="Requested",$D11<>"",TODAY()-$D11>14),"⚠ requested >14 days ago",IF(AND($C11="Yes",$H11<>"Received"),"⚠ outstanding item",""))))
I12: =IF($A12="","",IF($H12="Not Applicable","",IF(AND($H12="Requested",$D12<>"",TODAY()-$D12>14),"⚠ requested >14 days ago",IF(AND($C12="Yes",$H12<>"Received"),"⚠ outstanding item",""))))
I13: =IF($A13="","",IF($H13="Not Applicable","",IF(AND($H13="Requested",$D13<>"",TODAY()-$D13>14),"⚠ requested >14 days ago",IF(AND($C13="Yes",$H13<>"Received"),"⚠ outstanding item",""))))
I14: =IF($A14="","",IF($H14="Not Applicable","",IF(AND($H14="Requested",$D14<>"",TODAY()-$D14>14),"⚠ requested >14 days ago",IF(AND($C14="Yes",$H14<>"Received"),"⚠ outstanding item",""))))
I15: =IF($A15="","",IF($H15="Not Applicable","",IF(AND($H15="Requested",$D15<>"",TODAY()-$D15>14),"⚠ requested >14 days ago",IF(AND($C15="Yes",$H15<>"Received"),"⚠ outstanding item",""))))
I16: =IF($A16="","",IF($H16="Not Applicable","",IF(AND($H16="Requested",$D16<>"",TODAY()-$D16>14),"⚠ requested >14 days ago",IF(AND($C16="Yes",$H16<>"Received"),"⚠ outstanding item",""))))
I17: =IF($A17="","",IF($H17="Not Applicable","",IF(AND($H17="Requested",$D17<>"",TODAY()-$D17>14),"⚠ requested >14 days ago",IF(AND($C17="Yes",$H17<>"Received"),"⚠ outstanding item",""))))
I18: =IF($A18="","",IF($H18="Not Applicable","",IF(AND($H18="Requested",$D18<>"",TODAY()-$D18>14),"⚠ requested >14 days ago",IF(AND($C18="Yes",$H18<>"Received"),"⚠ outstanding item",""))))
I19: =IF($A19="","",IF($H19="Not Applicable","",IF(AND($H19="Requested",$D19<>"",TODAY()-$D19>14),"⚠ requested >14 days ago",IF(AND($C19="Yes",$H19<>"Received"),"⚠ outstanding item",""))))
I20: =IF($A20="","",IF($H20="Not Applicable","",IF(AND($H20="Requested",$D20<>"",TODAY()-$D20>14),"⚠ requested >14 days ago",IF(AND($C20="Yes",$H20<>"Received"),"⚠ outstanding item",""))))
I21: =IF($A21="","",IF($H21="Not Applicable","",IF(AND($H21="Requested",$D21<>"",TODAY()-$D21>14),"⚠ requested >14 days ago",IF(AND($C21="Yes",$H21<>"Received"),"⚠ outstanding item",""))))
... I153: =IF($A153="","",IF($H153="Not Applicable","",IF(AND($H153="Requested",$D153<>"",TODAY()-$D153>14),"⚠ requested >14 days ago",IF(AND($C153="Yes",$H153<>"Received"),"⚠ outstanding item",""))))

Sheet 08_CONTACTS_COMMUNICATION
A1: CONTACTS & COMMUNICATION
A3: Person/Entity | B3: Role | C3: Organization | D3: Email/Phone | E3: Last Contact | F3: Next Follow-up | G3: Related ID | H3: Issue/Topic | I3: Status | J3: Warning (auto)
A4: Doyle Estate Law Group | B4: Estate Attorney | C4: Doyle Estate Law Group | D4: contact@example-law.com | E4: 46269 | F4: 46297 | H4: Probate filing status | I4: Active | J4: =IF($A4="","",IF(AND($F4<>"",$F4<TODAY(),$I4<>"Resolved"),"⚠ follow-up due",""))
A5: Riverside Appraisals | B5: Appraiser | C5: Riverside Appraisals | D5: info@example-appraisals.com | E5: 46277 | F5: 46290 | G5: A2 | H5: Home appraisal scheduling | I5: Active | J5: =IF($A5="","",IF(AND($F5<>"",$F5<TODAY(),$I5<>"Resolved"),"⚠ follow-up due",""))
A6: Meridian Card Services | B6: Creditor | C6: Meridian Card Services | D6: claims@example-meridian.com | E6: 46272 | F6: 46292 | G6: L2 | H6: Disputing claimed balance | I6: Active | J6: =IF($A6="","",IF(AND($F6<>"",$F6<TODAY(),$I6<>"Resolved"),"⚠ follow-up due",""))
A7: First National Bank -- Estate Officer | B7: Bank Contact | C7: First National Bank | D7: estate@example-fnb.com | E7: 46217 | G7: A1 | H7: Estate account setup | I7: Resolved | J7: =IF($A7="","",IF(AND($F7<>"",$F7<TODAY(),$I7<>"Resolved"),"⚠ follow-up due",""))
J8: =IF($A8="","",IF(AND($F8<>"",$F8<TODAY(),$I8<>"Resolved"),"⚠ follow-up due",""))
J9: =IF($A9="","",IF(AND($F9<>"",$F9<TODAY(),$I9<>"Resolved"),"⚠ follow-up due",""))
J10: =IF($A10="","",IF(AND($F10<>"",$F10<TODAY(),$I10<>"Resolved"),"⚠ follow-up due",""))
J11: =IF($A11="","",IF(AND($F11<>"",$F11<TODAY(),$I11<>"Resolved"),"⚠ follow-up due",""))
J12: =IF($A12="","",IF(AND($F12<>"",$F12<TODAY(),$I12<>"Resolved"),"⚠ follow-up due",""))
J13: =IF($A13="","",IF(AND($F13<>"",$F13<TODAY(),$I13<>"Resolved"),"⚠ follow-up due",""))
J14: =IF($A14="","",IF(AND($F14<>"",$F14<TODAY(),$I14<>"Resolved"),"⚠ follow-up due",""))
J15: =IF($A15="","",IF(AND($F15<>"",$F15<TODAY(),$I15<>"Resolved"),"⚠ follow-up due",""))
J16: =IF($A16="","",IF(AND($F16<>"",$F16<TODAY(),$I16<>"Resolved"),"⚠ follow-up due",""))
J17: =IF($A17="","",IF(AND($F17<>"",$F17<TODAY(),$I17<>"Resolved"),"⚠ follow-up due",""))
J18: =IF($A18="","",IF(AND($F18<>"",$F18<TODAY(),$I18<>"Resolved"),"⚠ follow-up due",""))
J19: =IF($A19="","",IF(AND($F19<>"",$F19<TODAY(),$I19<>"Resolved"),"⚠ follow-up due",""))
... J103: =IF($A103="","",IF(AND($F103<>"",$F103<TODAY(),$I103<>"Resolved"),"⚠ follow-up due",""))

Sheet 09_BENEFICIARIES_DISTRIBUTIONS
A1: BENEFICIARIES & DISTRIBUTIONS
A2: Tracks your own entered records only — this workbook does not calculate legal entitlement.
A3: Beneficiary / Reference | B3: Contact Status | C3: Intended Share / Notes | D3: Planned Amount | E3: Amount Distributed | F3: Date Distributed | G3: Acknowledgment Received? | H3: Warning (auto)
A4: Nadia Doyle | B4: Confirmed | C4: Equal share, per will Article III | D4: 200000 | E4: 0 | G4: No | H4: =IF($A4="","",IF(AND(ISNUMBER($E4),$E4>0,$G4="No"),"⚠ distributed, no acknowledgment",""))
A5: Marcus Doyle | B5: Confirmed | C5: Equal share, per will Article III | D5: 200000 | E5: 0 | G5: No | H5: =IF($A5="","",IF(AND(ISNUMBER($E5),$E5>0,$G5="No"),"⚠ distributed, no acknowledgment",""))
A6: Cook County Humane Society | B6: Confirmed | C6: Specific bequest, per will Article V | D6: 5000 | E6: 5000 | F6: 46267 | G6: Yes | H6: =IF($A6="","",IF(AND(ISNUMBER($E6),$E6>0,$G6="No"),"⚠ distributed, no acknowledgment",""))
H7: =IF($A7="","",IF(AND(ISNUMBER($E7),$E7>0,$G7="No"),"⚠ distributed, no acknowledgment",""))
H8: =IF($A8="","",IF(AND(ISNUMBER($E8),$E8>0,$G8="No"),"⚠ distributed, no acknowledgment",""))
H9: =IF($A9="","",IF(AND(ISNUMBER($E9),$E9>0,$G9="No"),"⚠ distributed, no acknowledgment",""))
H10: =IF($A10="","",IF(AND(ISNUMBER($E10),$E10>0,$G10="No"),"⚠ distributed, no acknowledgment",""))
H11: =IF($A11="","",IF(AND(ISNUMBER($E11),$E11>0,$G11="No"),"⚠ distributed, no acknowledgment",""))
H12: =IF($A12="","",IF(AND(ISNUMBER($E12),$E12>0,$G12="No"),"⚠ distributed, no acknowledgment",""))
H13: =IF($A13="","",IF(AND(ISNUMBER($E13),$E13>0,$G13="No"),"⚠ distributed, no acknowledgment",""))
H14: =IF($A14="","",IF(AND(ISNUMBER($E14),$E14>0,$G14="No"),"⚠ distributed, no acknowledgment",""))
H15: =IF($A15="","",IF(AND(ISNUMBER($E15),$E15>0,$G15="No"),"⚠ distributed, no acknowledgment",""))
H16: =IF($A16="","",IF(AND(ISNUMBER($E16),$E16>0,$G16="No"),"⚠ distributed, no acknowledgment",""))
H17: =IF($A17="","",IF(AND(ISNUMBER($E17),$E17>0,$G17="No"),"⚠ distributed, no acknowledgment",""))
H18: =IF($A18="","",IF(AND(ISNUMBER($E18),$E18>0,$G18="No"),"⚠ distributed, no acknowledgment",""))
... H53: =IF($A53="","",IF(AND(ISNUMBER($E53),$E53>0,$G53="No"),"⚠ distributed, no acknowledgment",""))

Sheet 10_RECONCILIATION
A1: RECONCILIATION
A2: An ORGANIZATIONAL RECORD CHECK, not accounting or legal clearance.
A4: Starting Estate Cash | B4: ='00_START_HERE'!B8
A5: Recorded Transaction Inflows | B5: =SUM('05_ESTATE_TRANSACTIONS'!$G$4:$G$503)
A6: Recorded Transaction Outflows | B6: =SUM('05_ESTATE_TRANSACTIONS'!$H$4:$H$503)
A7: Expected Ending Estate Cash | B7: =B4+B5-B6
A8: Actual Estate Cash Balance | B8: ='00_START_HERE'!B9
A9: Reconciliation Difference (Actual - Expected) | B9: =B8-B7
A10: Transactions Missing Evidence (count) | B10: =COUNTIF('05_ESTATE_TRANSACTIONS'!$K$4:$K$503,"Missing")
A11: Transactions Flagged (both inflow & outflow) | B11: =COUNTIF('05_ESTATE_TRANSACTIONS'!$L$4:$L$503,"⚠ both inflow and outflow entered")
A13: Status | B13: =IF(AND(B4=0,B5=0,B6=0),"Not yet started",IF(AND(ABS(B9)<0.005,B10=0,B11=0),"Balanced","Review Needed"))
A15: A "Review Needed" or non-zero difference means the recorded transactions don't match your actual bank balance, or a record needs evidence — it is a prompt to review your entries, not a legal or accounting conclusion.

Sheet 11_CLOSEOUT_REVIEW
A1: CLOSEOUT REVIEW
A2: An organizational completeness check only — see the disclaimer below.
A4: Open Tasks (count) | B4: =COUNTIF('02_ACTION_ROADMAP'!$G$4:$G$203,"Open")+COUNTIF('02_ACTION_ROADMAP'!$G$4:$G$203,"Waiting")+COUNTIF('02_ACTION_ROADMAP'!$G$4:$G$203,"Blocked")
A5: Overdue Tasks (count) | B5: =COUNTIF('02_ACTION_ROADMAP'!$L$4:$L$203,"⚠ overdue")
A6: Unresolved Assets (count) | B6: =COUNTIF('03_ASSET_REGISTER'!$M$4:$M$103,"⚠ not located")+COUNTIF('03_ASSET_REGISTER'!$M$4:$M$103,"⚠ unresolved disposition")
A7: Unpaid Verified / Disputed Liabilities (count) | B7: =COUNTIF('04_LIABILITY_REGISTER'!$K$4:$K$103,"⚠ unpaid verified balance")+COUNTIF('04_LIABILITY_REGISTER'!$K$4:$K$103,"⚠ disputed item")
A8: Outstanding Documents (count) | B8: =COUNTIF('07_DOCUMENT_CONTROL'!$I$4:$I$153,"⚠ outstanding item")+COUNTIF('07_DOCUMENT_CONTROL'!$I$4:$I$153,"⚠ requested >14 days ago")
A9: Pending/Outstanding Reimbursements ($) | B9: =SUMIF('06_EXPENSES_REIMBURSEMENTS'!$L$4:$L$303,">0")
A10: Beneficiary-Record Flags (count) | B10: =COUNTIF('09_BENEFICIARIES_DISTRIBUTIONS'!$H$4:$H$53,"⚠ distributed, no acknowledgment")
A11: Reconciliation Difference ($) | B11: ='10_RECONCILIATION'!B9
A12: Transactions Missing Evidence (count) | B12: ='10_RECONCILIATION'!B10
A14: ORGANIZATIONAL CLOSEOUT STATUS | B14: =IF(NOT(OR('02_ACTION_ROADMAP'!$A$4<>"",'03_ASSET_REGISTER'!$A$4<>"",'04_LIABILITY_REGISTER'!$A$4<>"",'05_ESTATE_TRANSACTIONS'!$A$4<>"")),"SET UP ESTATE",IF(AND('10_RECONCILIATION'!B4=0,'10_RECONCILIATION'!B8=0),"NOT READY",IF(OR($B5>0,$B6>0,$B7>0,$B9>0,$B10>0,ABS($B11)>=0.005,$B12>0),"REVIEW","ORGANIZATION COMPLETE")))
A16: "Organization Complete" means this workbook's OWN organizational flags are clear. It never means probate is complete, taxes are complete, the estate is legally ready, or it is safe to distribute or close the estate. Always confirm final closeout with a qualified attorney or accountant.

Sheet 12_REPORTS_PRINT
A1: ESTATE SNAPSHOT (printable)
A3: Estate | B3: ='00_START_HERE'!B4
A4: Executor | B4: ='00_START_HERE'!B7
A5: Assets Identified | B5: =COUNTIF('03_ASSET_REGISTER'!$A$4:$A$103,"<>")
A6: Known Liabilities | B6: =COUNTIF('04_LIABILITY_REGISTER'!$A$4:$A$103,"<>")
A7: Expected Estate Cash | B7: ='10_RECONCILIATION'!B7
A8: Actual Estate Cash Balance | B8: ='10_RECONCILIATION'!B8
A9: Reconciliation Difference | B9: ='10_RECONCILIATION'!B9
A10: Organizational Closeout Status | B10: ='11_CLOSEOUT_REVIEW'!B14
A13: OPEN ISSUES SNAPSHOT
A14: Overdue Tasks | B14: ='11_CLOSEOUT_REVIEW'!B5
A15: Unresolved Assets | B15: ='11_CLOSEOUT_REVIEW'!B6
A16: Unpaid/Disputed Liabilities | B16: ='11_CLOSEOUT_REVIEW'!B7
A17: Outstanding Documents | B17: ='11_CLOSEOUT_REVIEW'!B8
A20: This is an organizational snapshot for your own records, not a legal, tax, or accounting document.
