Workbook

Sheet Start Here
A1: WELCOME — YOUR PREMIUM WEDDING BUDGET & PAYMENT SYSTEM
A2: This is a full wedding FINANCE system, not a wedding planner — no guest list, seating chart, or day-of timeline here. It tracks every dollar: what you've budgeted, what you owe each vendor and when, who's contributed what, and what happens to your numbers if your guest count changes. Pre-loaded with a realistic sample wedding so you can see it working before you enter your own numbers — replace the sample rows on Master Budget, Vendor & Payments, and Contributions with your own.
A4: Step 0 — Go to File > Make a Copy to save this to your own Google Drive. Always work from your own copy, never the original.
A6: QUICK NAVIGATION — click a tab name to jump there
A7: → Settings
A8: → Master Budget
A9: → Vendor & Payments
A10: → Cash-Flow Timeline
A11: → Contributions
A12: → Scenario Engine
A13: → Contingency
A14: → Dashboard
... A24: WHAT THE COLORS MEAN
A25: YELLOW | B25: YOU TYPE HERE.
A26: WHITE | B26: AUTOMATIC — calculated for you. Don't type over these; they pull from your Vendor & Payments entries.
A28: This is a planning tool, not a legal or contractual record — always keep your signed vendor contracts separately. Amounts are single-currency (your own); this tool does not perform currency conversion.

Sheet Settings
A1: SETTINGS
A3: Wedding Date | B3: 46550
A4: Total Target Budget | B4: 30000
A5: Estimated Guest Count | B5: 100
A6: Contingency Reserve (%) | B6: 0.1
A7: Today's Date (auto — do not edit) | B7: =TODAY()
A9: Note: | B9: All amounts are a single currency (your own) — this tool does not convert between currencies.

Sheet Master Budget
A1: MASTER WEDDING BUDGET
A3: Category | B3: Planned Budget | C3: Committed | D3: Actual Paid | E3: Remaining | F3: Variance | G3: Guest-Dependent? | H3: Status
A4: Venue & Reception | B4: 10000 | C4: =IF($A4="","",SUMIF('Vendor & Payments'!$A$4:$A$28,$A4,'Vendor & Payments'!$C$4:$C$28)) | D4: =IF($A4="","",SUMIF('Vendor & Payments'!$A$4:$A$28,$A4,'Vendor & Payments'!$E$4:$E$28)) | E4: =IF($A4="","",B4-D4) | F4: =IF($A4="",0,B4-C4) | G4: N | H4: =IF($A4="","",IF(OR(C4>B4,D4>B4),"⚠ OVER BUDGET","OK"))
A5: Catering & Bar | B5: 8000 | C5: =IF($A5="","",SUMIF('Vendor & Payments'!$A$4:$A$28,$A5,'Vendor & Payments'!$C$4:$C$28)) | D5: =IF($A5="","",SUMIF('Vendor & Payments'!$A$4:$A$28,$A5,'Vendor & Payments'!$E$4:$E$28)) | E5: =IF($A5="","",B5-D5) | F5: =IF($A5="",0,B5-C5) | G5: Y | H5: =IF($A5="","",IF(OR(C5>B5,D5>B5),"⚠ OVER BUDGET","OK"))
A6: Photography & Video | B6: 3000 | C6: =IF($A6="","",SUMIF('Vendor & Payments'!$A$4:$A$28,$A6,'Vendor & Payments'!$C$4:$C$28)) | D6: =IF($A6="","",SUMIF('Vendor & Payments'!$A$4:$A$28,$A6,'Vendor & Payments'!$E$4:$E$28)) | E6: =IF($A6="","",B6-D6) | F6: =IF($A6="",0,B6-C6) | G6: N | H6: =IF($A6="","",IF(OR(C6>B6,D6>B6),"⚠ OVER BUDGET","OK"))
A7: Attire & Beauty | B7: 2000 | C7: =IF($A7="","",SUMIF('Vendor & Payments'!$A$4:$A$28,$A7,'Vendor & Payments'!$C$4:$C$28)) | D7: =IF($A7="","",SUMIF('Vendor & Payments'!$A$4:$A$28,$A7,'Vendor & Payments'!$E$4:$E$28)) | E7: =IF($A7="","",B7-D7) | F7: =IF($A7="",0,B7-C7) | G7: N | H7: =IF($A7="","",IF(OR(C7>B7,D7>B7),"⚠ OVER BUDGET","OK"))
A8: Flowers & Decor | B8: 2000 | C8: =IF($A8="","",SUMIF('Vendor & Payments'!$A$4:$A$28,$A8,'Vendor & Payments'!$C$4:$C$28)) | D8: =IF($A8="","",SUMIF('Vendor & Payments'!$A$4:$A$28,$A8,'Vendor & Payments'!$E$4:$E$28)) | E8: =IF($A8="","",B8-D8) | F8: =IF($A8="",0,B8-C8) | G8: N | H8: =IF($A8="","",IF(OR(C8>B8,D8>B8),"⚠ OVER BUDGET","OK"))
A9: Music & Entertainment | B9: 1500 | C9: =IF($A9="","",SUMIF('Vendor & Payments'!$A$4:$A$28,$A9,'Vendor & Payments'!$C$4:$C$28)) | D9: =IF($A9="","",SUMIF('Vendor & Payments'!$A$4:$A$28,$A9,'Vendor & Payments'!$E$4:$E$28)) | E9: =IF($A9="","",B9-D9) | F9: =IF($A9="",0,B9-C9) | G9: N | H9: =IF($A9="","",IF(OR(C9>B9,D9>B9),"⚠ OVER BUDGET","OK"))
A10: Stationery & Invitations | B10: 500 | C10: =IF($A10="","",SUMIF('Vendor & Payments'!$A$4:$A$28,$A10,'Vendor & Payments'!$C$4:$C$28)) | D10: =IF($A10="","",SUMIF('Vendor & Payments'!$A$4:$A$28,$A10,'Vendor & Payments'!$E$4:$E$28)) | E10: =IF($A10="","",B10-D10) | F10: =IF($A10="",0,B10-C10) | G10: Y | H10: =IF($A10="","",IF(OR(C10>B10,D10>B10),"⚠ OVER BUDGET","OK"))
A11: Rings | B11: 1500 | C11: =IF($A11="","",SUMIF('Vendor & Payments'!$A$4:$A$28,$A11,'Vendor & Payments'!$C$4:$C$28)) | D11: =IF($A11="","",SUMIF('Vendor & Payments'!$A$4:$A$28,$A11,'Vendor & Payments'!$E$4:$E$28)) | E11: =IF($A11="","",B11-D11) | F11: =IF($A11="",0,B11-C11) | G11: N | H11: =IF($A11="","",IF(OR(C11>B11,D11>B11),"⚠ OVER BUDGET","OK"))
A12: Hair & Makeup | B12: 800 | C12: =IF($A12="","",SUMIF('Vendor & Payments'!$A$4:$A$28,$A12,'Vendor & Payments'!$C$4:$C$28)) | D12: =IF($A12="","",SUMIF('Vendor & Payments'!$A$4:$A$28,$A12,'Vendor & Payments'!$E$4:$E$28)) | E12: =IF($A12="","",B12-D12) | F12: =IF($A12="",0,B12-C12) | G12: N | H12: =IF($A12="","",IF(OR(C12>B12,D12>B12),"⚠ OVER BUDGET","OK"))
A13: Transportation | B13: 500 | C13: =IF($A13="","",SUMIF('Vendor & Payments'!$A$4:$A$28,$A13,'Vendor & Payments'!$C$4:$C$28)) | D13: =IF($A13="","",SUMIF('Vendor & Payments'!$A$4:$A$28,$A13,'Vendor & Payments'!$E$4:$E$28)) | E13: =IF($A13="","",B13-D13) | F13: =IF($A13="",0,B13-C13) | G13: N | H13: =IF($A13="","",IF(OR(C13>B13,D13>B13),"⚠ OVER BUDGET","OK"))
A14: Officiant & Ceremony | B14: 500 | C14: =IF($A14="","",SUMIF('Vendor & Payments'!$A$4:$A$28,$A14,'Vendor & Payments'!$C$4:$C$28)) | D14: =IF($A14="","",SUMIF('Vendor & Payments'!$A$4:$A$28,$A14,'Vendor & Payments'!$E$4:$E$28)) | E14: =IF($A14="","",B14-D14) | F14: =IF($A14="",0,B14-C14) | G14: N | H14: =IF($A14="","",IF(OR(C14>B14,D14>B14),"⚠ OVER BUDGET","OK"))
A15: Favors & Gifts | B15: 500 | C15: =IF($A15="","",SUMIF('Vendor & Payments'!$A$4:$A$28,$A15,'Vendor & Payments'!$C$4:$C$28)) | D15: =IF($A15="","",SUMIF('Vendor & Payments'!$A$4:$A$28,$A15,'Vendor & Payments'!$E$4:$E$28)) | E15: =IF($A15="","",B15-D15) | F15: =IF($A15="",0,B15-C15) | G15: Y | H15: =IF($A15="","",IF(OR(C15>B15,D15>B15),"⚠ OVER BUDGET","OK"))
... A17: Miscellaneous | B17: 700 | C17: =IF($A17="","",SUMIF('Vendor & Payments'!$A$4:$A$28,$A17,'Vendor & Payments'!$C$4:$C$28)) | D17: =IF($A17="","",SUMIF('Vendor & Payments'!$A$4:$A$28,$A17,'Vendor & Payments'!$E$4:$E$28)) | E17: =IF($A17="","",B17-D17) | F17: =IF($A17="",0,B17-C17) | G17: N | H17: =IF($A17="","",IF(OR(C17>B17,D17>B17),"⚠ OVER BUDGET","OK"))
B18: 0 | C18: =IF($A18="","",SUMIF('Vendor & Payments'!$A$4:$A$28,$A18,'Vendor & Payments'!$C$4:$C$28)) | D18: =IF($A18="","",SUMIF('Vendor & Payments'!$A$4:$A$28,$A18,'Vendor & Payments'!$E$4:$E$28)) | E18: =IF($A18="","",B18-D18) | F18: =IF($A18="",0,B18-C18) | G18: N | H18: =IF($A18="","",IF(OR(C18>B18,D18>B18),"⚠ OVER BUDGET","OK"))
A19: TOTAL | B19: =SUM(B4:B18) | C19: =SUM(C4:C18) | D19: =SUM(D4:D18) | E19: =SUM(E4:E18) | F19: =SUM(F4:F18)

Sheet Vendor & Payments
A1: VENDOR & PAYMENT SYSTEM
A2: Enter each vendor once. Balance, cash-flow timing, and status update automatically — you never re-enter these numbers elsewhere.
A3: Category | B3: Vendor Name | C3: Contracted Amount | D3: Deposit Required | E3: Total Paid To Date | F3: Balance Remaining | G3: Next Payment Due Date | H3: Paid By | I3: Status
A4: Venue & Reception | B4: Grandview Estate | C4: 10000 | D4: 2000 | E4: 2000 | F4: =IF($B4="",0,IF(AND(ISNUMBER(C4),ISNUMBER(E4)),MAX(C4-E4,0),0)) | G4: 46339 | H4: Partner 1 | I4: =IF($B4="","",IF(OR(NOT(ISNUMBER(C4)),NOT(ISNUMBER(E4))),"⚠ CHECK ENTRY (non-numeric $)",IF(F4<=0,"PAID IN FULL",IF(G4="","NO DUE DATE",IF(G4<Settings!$B$7,"OVERDUE",IF(G4-Settings!$B$7<=14,"DUE SOON","UPCOMING"))))))
A5: Catering & Bar | B5: Tasty Catering Co | C5: 8500 | D5: 1000 | E5: 8500 | F5: =IF($B5="",0,IF(AND(ISNUMBER(C5),ISNUMBER(E5)),MAX(C5-E5,0),0)) | G5: 46249 | H5: Partner 2 | I5: =IF($B5="","",IF(OR(NOT(ISNUMBER(C5)),NOT(ISNUMBER(E5))),"⚠ CHECK ENTRY (non-numeric $)",IF(F5<=0,"PAID IN FULL",IF(G5="","NO DUE DATE",IF(G5<Settings!$B$7,"OVERDUE",IF(G5-Settings!$B$7<=14,"DUE SOON","UPCOMING"))))))
A6: Photography & Video | B6: Lens & Light Studio | C6: 3000 | D6: 500 | E6: 500 | F6: =IF($B6="",0,IF(AND(ISNUMBER(C6),ISNUMBER(E6)),MAX(C6-E6,0),0)) | G6: 46284 | H6: Family | I6: =IF($B6="","",IF(OR(NOT(ISNUMBER(C6)),NOT(ISNUMBER(E6))),"⚠ CHECK ENTRY (non-numeric $)",IF(F6<=0,"PAID IN FULL",IF(G6="","NO DUE DATE",IF(G6<Settings!$B$7,"OVERDUE",IF(G6-Settings!$B$7<=14,"DUE SOON","UPCOMING"))))))
A7: Rings | B7: Downtown Jewelers | C7: 1500 | D7: 0 | E7: 0 | F7: =IF($B7="",0,IF(AND(ISNUMBER(C7),ISNUMBER(E7)),MAX(C7-E7,0),0)) | G7: 46274 | H7: Partner 1 | I7: =IF($B7="","",IF(OR(NOT(ISNUMBER(C7)),NOT(ISNUMBER(E7))),"⚠ CHECK ENTRY (non-numeric $)",IF(F7<=0,"PAID IN FULL",IF(G7="","NO DUE DATE",IF(G7<Settings!$B$7,"OVERDUE",IF(G7-Settings!$B$7<=14,"DUE SOON","UPCOMING"))))))
A8: Flowers & Decor | B8: Bloom & Co | C8: 1800 | D8: 300 | E8: 300 | F8: =IF($B8="",0,IF(AND(ISNUMBER(C8),ISNUMBER(E8)),MAX(C8-E8,0),0)) | G8: 46479 | H8: Partner 2 | I8: =IF($B8="","",IF(OR(NOT(ISNUMBER(C8)),NOT(ISNUMBER(E8))),"⚠ CHECK ENTRY (non-numeric $)",IF(F8<=0,"PAID IN FULL",IF(G8="","NO DUE DATE",IF(G8<Settings!$B$7,"OVERDUE",IF(G8-Settings!$B$7<=14,"DUE SOON","UPCOMING"))))))
F9: =IF($B9="",0,IF(AND(ISNUMBER(C9),ISNUMBER(E9)),MAX(C9-E9,0),0)) | I9: =IF($B9="","",IF(OR(NOT(ISNUMBER(C9)),NOT(ISNUMBER(E9))),"⚠ CHECK ENTRY (non-numeric $)",IF(F9<=0,"PAID IN FULL",IF(G9="","NO DUE DATE",IF(G9<Settings!$B$7,"OVERDUE",IF(G9-Settings!$B$7<=14,"DUE SOON","UPCOMING"))))))
F10: =IF($B10="",0,IF(AND(ISNUMBER(C10),ISNUMBER(E10)),MAX(C10-E10,0),0)) | I10: =IF($B10="","",IF(OR(NOT(ISNUMBER(C10)),NOT(ISNUMBER(E10))),"⚠ CHECK ENTRY (non-numeric $)",IF(F10<=0,"PAID IN FULL",IF(G10="","NO DUE DATE",IF(G10<Settings!$B$7,"OVERDUE",IF(G10-Settings!$B$7<=14,"DUE SOON","UPCOMING"))))))
F11: =IF($B11="",0,IF(AND(ISNUMBER(C11),ISNUMBER(E11)),MAX(C11-E11,0),0)) | I11: =IF($B11="","",IF(OR(NOT(ISNUMBER(C11)),NOT(ISNUMBER(E11))),"⚠ CHECK ENTRY (non-numeric $)",IF(F11<=0,"PAID IN FULL",IF(G11="","NO DUE DATE",IF(G11<Settings!$B$7,"OVERDUE",IF(G11-Settings!$B$7<=14,"DUE SOON","UPCOMING"))))))
F12: =IF($B12="",0,IF(AND(ISNUMBER(C12),ISNUMBER(E12)),MAX(C12-E12,0),0)) | I12: =IF($B12="","",IF(OR(NOT(ISNUMBER(C12)),NOT(ISNUMBER(E12))),"⚠ CHECK ENTRY (non-numeric $)",IF(F12<=0,"PAID IN FULL",IF(G12="","NO DUE DATE",IF(G12<Settings!$B$7,"OVERDUE",IF(G12-Settings!$B$7<=14,"DUE SOON","UPCOMING"))))))
F13: =IF($B13="",0,IF(AND(ISNUMBER(C13),ISNUMBER(E13)),MAX(C13-E13,0),0)) | I13: =IF($B13="","",IF(OR(NOT(ISNUMBER(C13)),NOT(ISNUMBER(E13))),"⚠ CHECK ENTRY (non-numeric $)",IF(F13<=0,"PAID IN FULL",IF(G13="","NO DUE DATE",IF(G13<Settings!$B$7,"OVERDUE",IF(G13-Settings!$B$7<=14,"DUE SOON","UPCOMING"))))))
F14: =IF($B14="",0,IF(AND(ISNUMBER(C14),ISNUMBER(E14)),MAX(C14-E14,0),0)) | I14: =IF($B14="","",IF(OR(NOT(ISNUMBER(C14)),NOT(ISNUMBER(E14))),"⚠ CHECK ENTRY (non-numeric $)",IF(F14<=0,"PAID IN FULL",IF(G14="","NO DUE DATE",IF(G14<Settings!$B$7,"OVERDUE",IF(G14-Settings!$B$7<=14,"DUE SOON","UPCOMING"))))))
F15: =IF($B15="",0,IF(AND(ISNUMBER(C15),ISNUMBER(E15)),MAX(C15-E15,0),0)) | I15: =IF($B15="","",IF(OR(NOT(ISNUMBER(C15)),NOT(ISNUMBER(E15))),"⚠ CHECK ENTRY (non-numeric $)",IF(F15<=0,"PAID IN FULL",IF(G15="","NO DUE DATE",IF(G15<Settings!$B$7,"OVERDUE",IF(G15-Settings!$B$7<=14,"DUE SOON","UPCOMING"))))))
F16: =IF($B16="",0,IF(AND(ISNUMBER(C16),ISNUMBER(E16)),MAX(C16-E16,0),0)) | I16: =IF($B16="","",IF(OR(NOT(ISNUMBER(C16)),NOT(ISNUMBER(E16))),"⚠ CHECK ENTRY (non-numeric $)",IF(F16<=0,"PAID IN FULL",IF(G16="","NO DUE DATE",IF(G16<Settings!$B$7,"OVERDUE",IF(G16-Settings!$B$7<=14,"DUE SOON","UPCOMING"))))))
F17: =IF($B17="",0,IF(AND(ISNUMBER(C17),ISNUMBER(E17)),MAX(C17-E17,0),0)) | I17: =IF($B17="","",IF(OR(NOT(ISNUMBER(C17)),NOT(ISNUMBER(E17))),"⚠ CHECK ENTRY (non-numeric $)",IF(F17<=0,"PAID IN FULL",IF(G17="","NO DUE DATE",IF(G17<Settings!$B$7,"OVERDUE",IF(G17-Settings!$B$7<=14,"DUE SOON","UPCOMING"))))))
F18: =IF($B18="",0,IF(AND(ISNUMBER(C18),ISNUMBER(E18)),MAX(C18-E18,0),0)) | I18: =IF($B18="","",IF(OR(NOT(ISNUMBER(C18)),NOT(ISNUMBER(E18))),"⚠ CHECK ENTRY (non-numeric $)",IF(F18<=0,"PAID IN FULL",IF(G18="","NO DUE DATE",IF(G18<Settings!$B$7,"OVERDUE",IF(G18-Settings!$B$7<=14,"DUE SOON","UPCOMING"))))))
F19: =IF($B19="",0,IF(AND(ISNUMBER(C19),ISNUMBER(E19)),MAX(C19-E19,0),0)) | I19: =IF($B19="","",IF(OR(NOT(ISNUMBER(C19)),NOT(ISNUMBER(E19))),"⚠ CHECK ENTRY (non-numeric $)",IF(F19<=0,"PAID IN FULL",IF(G19="","NO DUE DATE",IF(G19<Settings!$B$7,"OVERDUE",IF(G19-Settings!$B$7<=14,"DUE SOON","UPCOMING"))))))
F20: =IF($B20="",0,IF(AND(ISNUMBER(C20),ISNUMBER(E20)),MAX(C20-E20,0),0)) | I20: =IF($B20="","",IF(OR(NOT(ISNUMBER(C20)),NOT(ISNUMBER(E20))),"⚠ CHECK ENTRY (non-numeric $)",IF(F20<=0,"PAID IN FULL",IF(G20="","NO DUE DATE",IF(G20<Settings!$B$7,"OVERDUE",IF(G20-Settings!$B$7<=14,"DUE SOON","UPCOMING"))))))
... F28: =IF($B28="",0,IF(AND(ISNUMBER(C28),ISNUMBER(E28)),MAX(C28-E28,0),0)) | I28: =IF($B28="","",IF(OR(NOT(ISNUMBER(C28)),NOT(ISNUMBER(E28))),"⚠ CHECK ENTRY (non-numeric $)",IF(F28<=0,"PAID IN FULL",IF(G28="","NO DUE DATE",IF(G28<Settings!$B$7,"OVERDUE",IF(G28-Settings!$B$7<=14,"DUE SOON","UPCOMING"))))))
A29: TOTAL | C29: =SUM(C4:C28) | D29: =SUM(D4:D28) | E29: =SUM(E4:E28) | F29: =SUM(F4:F28)
A31: Vendor $ in categories that don't match Master Budget: | B31: =SUMPRODUCT((B4:B28<>"")*ISNA(MATCH(A4:A28,'Master Budget'!$A$4:$A$18,0)),C4:C28)
A32: =IF(B31>0,"⚠ "&TEXT(B31,"$#,##0")&" of vendor spend uses a Category that doesn't exactly match a Master Budget row — it will NOT show up in your Master Budget totals. Check for typos, or pick the category from the dropdown instead of typing it.","")

Sheet Cash-Flow Timeline
A1: CASH-FLOW TIMELINE
A2: Built automatically from your Vendor & Payments due dates and balances — nothing here is re-typed. The first month shown includes any overdue balances too, not just amounts newly due this month.
A3: Timeline starts (auto): | B3: =EOMONTH(Settings!$B$7,-1)+1
A5: Month | B5: Amount Due This Month | C5: Cumulative Planned Spend
A6: =$B$3 | B6: =SUMPRODUCT(('Vendor & Payments'!$G$4:$G$28<>"")*('Vendor & Payments'!$G$4:$G$28<=EOMONTH($A6,0))*'Vendor & Payments'!$F$4:$F$28) | C6: =B6
A7: =EDATE(A6,1) | B7: =SUMPRODUCT(('Vendor & Payments'!$G$4:$G$28<>"")*(TEXT('Vendor & Payments'!$G$4:$G$28,"yyyy-mm")=TEXT($A7,"yyyy-mm"))*'Vendor & Payments'!$F$4:$F$28) | C7: =C6+B7
A8: =EDATE(A7,1) | B8: =SUMPRODUCT(('Vendor & Payments'!$G$4:$G$28<>"")*(TEXT('Vendor & Payments'!$G$4:$G$28,"yyyy-mm")=TEXT($A8,"yyyy-mm"))*'Vendor & Payments'!$F$4:$F$28) | C8: =C7+B8
A9: =EDATE(A8,1) | B9: =SUMPRODUCT(('Vendor & Payments'!$G$4:$G$28<>"")*(TEXT('Vendor & Payments'!$G$4:$G$28,"yyyy-mm")=TEXT($A9,"yyyy-mm"))*'Vendor & Payments'!$F$4:$F$28) | C9: =C8+B9
A10: =EDATE(A9,1) | B10: =SUMPRODUCT(('Vendor & Payments'!$G$4:$G$28<>"")*(TEXT('Vendor & Payments'!$G$4:$G$28,"yyyy-mm")=TEXT($A10,"yyyy-mm"))*'Vendor & Payments'!$F$4:$F$28) | C10: =C9+B10
A11: =EDATE(A10,1) | B11: =SUMPRODUCT(('Vendor & Payments'!$G$4:$G$28<>"")*(TEXT('Vendor & Payments'!$G$4:$G$28,"yyyy-mm")=TEXT($A11,"yyyy-mm"))*'Vendor & Payments'!$F$4:$F$28) | C11: =C10+B11
A12: =EDATE(A11,1) | B12: =SUMPRODUCT(('Vendor & Payments'!$G$4:$G$28<>"")*(TEXT('Vendor & Payments'!$G$4:$G$28,"yyyy-mm")=TEXT($A12,"yyyy-mm"))*'Vendor & Payments'!$F$4:$F$28) | C12: =C11+B12
A13: =EDATE(A12,1) | B13: =SUMPRODUCT(('Vendor & Payments'!$G$4:$G$28<>"")*(TEXT('Vendor & Payments'!$G$4:$G$28,"yyyy-mm")=TEXT($A13,"yyyy-mm"))*'Vendor & Payments'!$F$4:$F$28) | C13: =C12+B13
A14: =EDATE(A13,1) | B14: =SUMPRODUCT(('Vendor & Payments'!$G$4:$G$28<>"")*(TEXT('Vendor & Payments'!$G$4:$G$28,"yyyy-mm")=TEXT($A14,"yyyy-mm"))*'Vendor & Payments'!$F$4:$F$28) | C14: =C13+B14
A15: =EDATE(A14,1) | B15: =SUMPRODUCT(('Vendor & Payments'!$G$4:$G$28<>"")*(TEXT('Vendor & Payments'!$G$4:$G$28,"yyyy-mm")=TEXT($A15,"yyyy-mm"))*'Vendor & Payments'!$F$4:$F$28) | C15: =C14+B15
A16: =EDATE(A15,1) | B16: =SUMPRODUCT(('Vendor & Payments'!$G$4:$G$28<>"")*(TEXT('Vendor & Payments'!$G$4:$G$28,"yyyy-mm")=TEXT($A16,"yyyy-mm"))*'Vendor & Payments'!$F$4:$F$28) | C16: =C15+B16
A17: =EDATE(A16,1) | B17: =SUMPRODUCT(('Vendor & Payments'!$G$4:$G$28<>"")*(TEXT('Vendor & Payments'!$G$4:$G$28,"yyyy-mm")=TEXT($A17,"yyyy-mm"))*'Vendor & Payments'!$F$4:$F$28) | C17: =C16+B17
A18: =EDATE(A17,1) | B18: =SUMPRODUCT(('Vendor & Payments'!$G$4:$G$28<>"")*(TEXT('Vendor & Payments'!$G$4:$G$28,"yyyy-mm")=TEXT($A18,"yyyy-mm"))*'Vendor & Payments'!$F$4:$F$28) | C18: =C17+B18
... A23: =EDATE(A22,1) | B23: =SUMPRODUCT(('Vendor & Payments'!$G$4:$G$28<>"")*(TEXT('Vendor & Payments'!$G$4:$G$28,"yyyy-mm")=TEXT($A23,"yyyy-mm"))*'Vendor & Payments'!$F$4:$F$28) | C23: =C22+B23
A25: Payments due beyond this 18-month window: | B25: =SUMPRODUCT(('Vendor & Payments'!$G$4:$G$28<>"")*('Vendor & Payments'!$G$4:$G$28>$A$23)*'Vendor & Payments'!$F$4:$F$28)
A26: =IF(B25>0,"⚠ "&TEXT(B25,"$#,##0")&" in payments fall beyond this 18-month timeline — extend the table if your engagement is longer than that.","")

Sheet Contributions
A1: CONTRIBUTION TRACKER
A3: Contributor Name | B3: Role | C3: Promised Amount | D3: Received Amount | E3: Remaining Promised | F3: Overpaid Amount | G3: Paid Directly (Vendors)
A4: Partner 1 | B4: Partner 1 | C4: 15000 | D4: 10000 | E4: =IF($A4="","",MAX(C4-D4,0)) | F4: =IF($A4="","",MAX(D4-C4,0)) | G4: =IF($A4="","",SUMIF('Vendor & Payments'!$H$4:$H$28,$A4,'Vendor & Payments'!$E$4:$E$28))
A5: Partner 2 | B5: Partner 2 | C5: 10000 | D5: 10000 | E5: =IF($A5="","",MAX(C5-D5,0)) | F5: =IF($A5="","",MAX(D5-C5,0)) | G5: =IF($A5="","",SUMIF('Vendor & Payments'!$H$4:$H$28,$A5,'Vendor & Payments'!$E$4:$E$28))
A6: Family | B6: Family | C6: 5000 | D6: 3000 | E6: =IF($A6="","",MAX(C6-D6,0)) | F6: =IF($A6="","",MAX(D6-C6,0)) | G6: =IF($A6="","",SUMIF('Vendor & Payments'!$H$4:$H$28,$A6,'Vendor & Payments'!$E$4:$E$28))
E7: =IF($A7="","",MAX(C7-D7,0)) | F7: =IF($A7="","",MAX(D7-C7,0)) | G7: =IF($A7="","",SUMIF('Vendor & Payments'!$H$4:$H$28,$A7,'Vendor & Payments'!$E$4:$E$28))
E8: =IF($A8="","",MAX(C8-D8,0)) | F8: =IF($A8="","",MAX(D8-C8,0)) | G8: =IF($A8="","",SUMIF('Vendor & Payments'!$H$4:$H$28,$A8,'Vendor & Payments'!$E$4:$E$28))
E9: =IF($A9="","",MAX(C9-D9,0)) | F9: =IF($A9="","",MAX(D9-C9,0)) | G9: =IF($A9="","",SUMIF('Vendor & Payments'!$H$4:$H$28,$A9,'Vendor & Payments'!$E$4:$E$28))
E10: =IF($A10="","",MAX(C10-D10,0)) | F10: =IF($A10="","",MAX(D10-C10,0)) | G10: =IF($A10="","",SUMIF('Vendor & Payments'!$H$4:$H$28,$A10,'Vendor & Payments'!$E$4:$E$28))
E11: =IF($A11="","",MAX(C11-D11,0)) | F11: =IF($A11="","",MAX(D11-C11,0)) | G11: =IF($A11="","",SUMIF('Vendor & Payments'!$H$4:$H$28,$A11,'Vendor & Payments'!$E$4:$E$28))
E12: =IF($A12="","",MAX(C12-D12,0)) | F12: =IF($A12="","",MAX(D12-C12,0)) | G12: =IF($A12="","",SUMIF('Vendor & Payments'!$H$4:$H$28,$A12,'Vendor & Payments'!$E$4:$E$28))
E13: =IF($A13="","",MAX(C13-D13,0)) | F13: =IF($A13="","",MAX(D13-C13,0)) | G13: =IF($A13="","",SUMIF('Vendor & Payments'!$H$4:$H$28,$A13,'Vendor & Payments'!$E$4:$E$28))
A14: TOTAL | C14: =SUM(C4:C13) | D14: =SUM(D4:D13) | E14: =SUM(E4:E13) | F14: =SUM(F4:F13) | G14: =SUM(G4:G13)
A16: RECONCILIATION
A17: Total Contributions Received | B17: =D14
A18: Total Spent on Vendors To Date | B18: =SUM('Vendor & Payments'!$E$4:$E$28)
A19: Unallocated / Remaining Funds | B19: =B17-B18
A20: =IF(B19<0,"⚠ Recorded vendor payments exceed recorded contributions received — some payments may be funded directly and not yet logged as ''received''.","")

Sheet Scenario Engine
A1: COST-PER-GUEST SCENARIO ENGINE
A2: Only categories marked Guest-Dependent on Master Budget scale with guest count below — fixed costs (venue, photography, dress) stay constant.
A4: Baseline Guest Count (from Settings) | B4: =Settings!$B$5
A5: Scenario Guest Count (try a different number) | B5: =Settings!$B$5
A7: Category | B7: Guest-Dependent? | C7: Current Planned (baseline) | D7: Implied Per-Guest Cost | E7: Scenario Cost
A8: =IF('Master Budget'!A4="","",'Master Budget'!A4) | B8: ='Master Budget'!G4 | C8: ='Master Budget'!B4 | D8: =IF($A8="","",IF(B8="Y",IFERROR(C8/Settings!$B$5,0),"")) | E8: =IF($A8="","",IF(B8="Y",D8*$B$5,C8))
A9: =IF('Master Budget'!A5="","",'Master Budget'!A5) | B9: ='Master Budget'!G5 | C9: ='Master Budget'!B5 | D9: =IF($A9="","",IF(B9="Y",IFERROR(C9/Settings!$B$5,0),"")) | E9: =IF($A9="","",IF(B9="Y",D9*$B$5,C9))
A10: =IF('Master Budget'!A6="","",'Master Budget'!A6) | B10: ='Master Budget'!G6 | C10: ='Master Budget'!B6 | D10: =IF($A10="","",IF(B10="Y",IFERROR(C10/Settings!$B$5,0),"")) | E10: =IF($A10="","",IF(B10="Y",D10*$B$5,C10))
A11: =IF('Master Budget'!A7="","",'Master Budget'!A7) | B11: ='Master Budget'!G7 | C11: ='Master Budget'!B7 | D11: =IF($A11="","",IF(B11="Y",IFERROR(C11/Settings!$B$5,0),"")) | E11: =IF($A11="","",IF(B11="Y",D11*$B$5,C11))
A12: =IF('Master Budget'!A8="","",'Master Budget'!A8) | B12: ='Master Budget'!G8 | C12: ='Master Budget'!B8 | D12: =IF($A12="","",IF(B12="Y",IFERROR(C12/Settings!$B$5,0),"")) | E12: =IF($A12="","",IF(B12="Y",D12*$B$5,C12))
A13: =IF('Master Budget'!A9="","",'Master Budget'!A9) | B13: ='Master Budget'!G9 | C13: ='Master Budget'!B9 | D13: =IF($A13="","",IF(B13="Y",IFERROR(C13/Settings!$B$5,0),"")) | E13: =IF($A13="","",IF(B13="Y",D13*$B$5,C13))
A14: =IF('Master Budget'!A10="","",'Master Budget'!A10) | B14: ='Master Budget'!G10 | C14: ='Master Budget'!B10 | D14: =IF($A14="","",IF(B14="Y",IFERROR(C14/Settings!$B$5,0),"")) | E14: =IF($A14="","",IF(B14="Y",D14*$B$5,C14))
A15: =IF('Master Budget'!A11="","",'Master Budget'!A11) | B15: ='Master Budget'!G11 | C15: ='Master Budget'!B11 | D15: =IF($A15="","",IF(B15="Y",IFERROR(C15/Settings!$B$5,0),"")) | E15: =IF($A15="","",IF(B15="Y",D15*$B$5,C15))
A16: =IF('Master Budget'!A12="","",'Master Budget'!A12) | B16: ='Master Budget'!G12 | C16: ='Master Budget'!B12 | D16: =IF($A16="","",IF(B16="Y",IFERROR(C16/Settings!$B$5,0),"")) | E16: =IF($A16="","",IF(B16="Y",D16*$B$5,C16))
A17: =IF('Master Budget'!A13="","",'Master Budget'!A13) | B17: ='Master Budget'!G13 | C17: ='Master Budget'!B13 | D17: =IF($A17="","",IF(B17="Y",IFERROR(C17/Settings!$B$5,0),"")) | E17: =IF($A17="","",IF(B17="Y",D17*$B$5,C17))
A18: =IF('Master Budget'!A14="","",'Master Budget'!A14) | B18: ='Master Budget'!G14 | C18: ='Master Budget'!B14 | D18: =IF($A18="","",IF(B18="Y",IFERROR(C18/Settings!$B$5,0),"")) | E18: =IF($A18="","",IF(B18="Y",D18*$B$5,C18))
A19: =IF('Master Budget'!A15="","",'Master Budget'!A15) | B19: ='Master Budget'!G15 | C19: ='Master Budget'!B15 | D19: =IF($A19="","",IF(B19="Y",IFERROR(C19/Settings!$B$5,0),"")) | E19: =IF($A19="","",IF(B19="Y",D19*$B$5,C19))
... A22: =IF('Master Budget'!A18="","",'Master Budget'!A18) | B22: ='Master Budget'!G18 | C22: ='Master Budget'!B18 | D22: =IF($A22="","",IF(B22="Y",IFERROR(C22/Settings!$B$5,0),"")) | E22: =IF($A22="","",IF(B22="Y",D22*$B$5,C22))
A23: TOTAL | C23: =SUM(C8:C22) | E23: =SUM(E8:E22)
A25: Baseline Total Planned | B25: =C23
A26: Scenario Total (at Scenario Guest Count) | B26: =E23
A27: Financial Effect of Guest-Count Change | B27: =B26-B25
A29: =IF(Settings!$B$5=0,"Set a non-zero Estimated Guest Count on Settings to enable per-guest scenario math.","")

Sheet Contingency
A1: CONTINGENCY / BUFFER
A3: Contingency Reserve (%) | B3: =Settings!$B$6
A4: Base Planned Budget | B4: ='Master Budget'!$B$19
A5: Contingency Amount | B5: =B4*B3
A6: Effective Available Budget | B6: =B4+B5
A7: Total Category Overage | B7: =-SUMPRODUCT(('Master Budget'!$F$4:$F$18<0)*'Master Budget'!$F$4:$F$18)
A8: Contingency Remaining | B8: =B5-B7
A10: =IF(B8<0,"⚠ CONTINGENCY EXHAUSTED — over by "&TEXT(-B8,"$#,##0"),"OK")

Sheet Dashboard
A1: DASHBOARD
A3: Total Target Budget | B3: =Settings!$B$4
A4: Total Planned (Master Budget) | B4: ='Master Budget'!$B$19
A5: Total Committed | B5: ='Master Budget'!$C$19
A6: Total Paid | B6: ='Master Budget'!$D$19
A7: Total Remaining | B7: ='Master Budget'!$E$19
A8: Budget Variance | B8: ='Master Budget'!$F$19
A9: Upcoming Payments — Count (next 14 days) | B9: =COUNTIF('Vendor & Payments'!$I$4:$I$28,"DUE SOON")
A10: Upcoming Payments — Amount | B10: =SUMIF('Vendor & Payments'!$I$4:$I$28,"DUE SOON",'Vendor & Payments'!$F$4:$F$28)
A11: Overdue Payments — Count | B11: =COUNTIF('Vendor & Payments'!$I$4:$I$28,"OVERDUE")
A12: Overdue Payments — Amount | B12: =SUMIF('Vendor & Payments'!$I$4:$I$28,"OVERDUE",'Vendor & Payments'!$F$4:$F$28)
A13: Contributions Received | B13: =Contributions!$D$14
A14: Contributions Outstanding | B14: =Contributions!$E$14
A15: Cost Per Guest (Planned) | B15: =IFERROR('Master Budget'!$B$19/Settings!$B$5,"N/A")
A16: Contingency Remaining | B16: =Contingency!$B$8
A18: =IF(B6>B3,"⚠ TOTAL PAID EXCEEDS YOUR TARGET BUDGET","OK")

Sheet Chart
A1: VISUAL SUMMARY
A3: Planned vs. Actual by Category
A25: Cash-Flow Timeline — Amount Due by Month
